Workbook

Sheet Grid de recoleccion
A1: Grid de recolección — corpus multi-dominio v2 (5 medios × 5 dominios, 500 oraciones)
A2: Recolección CERRADA y auditada. Los objetivos reflejan exactamente lo recolectado: 100 oraciones por dominio, 500 en total. El % de avance mide la ANOTACIÓN: arranca en 0% y sube a medida que se llena la columna 'direccion' de cada oración en la hoja 'Corpus - oraciones'.
A4: Medio | B4: Tema | C4: Objetivo oraciones (dura) | D4: Objetivo oraciones (opinión/análisis) | E4: Objetivo total | F4: Artículos de origen (dura) | G4: Artículos de origen (opinión) | H4: Oraciones ya anotadas | I4: % avance | J4: Estado | K4: Notas
A5: Infobae Colombia | B5: Política | C5: 13 | D5: 0 | E5: =C5+D5 | F5: 6 | G5: 0 | H5: =SUMIFS('Corpus - oraciones'!$AD$5:$AD$600,'Corpus - oraciones'!$C$5:$C$600,A5,'Corpus - oraciones'!$D$5:$D$600,B5) | I5: =IFERROR(H5/E5,0) | J5: Pendiente | K5: Infobae no tiene sección de opinión propia de Colombia: su cuota es 100% noticia dura.
A6: El Tiempo | B6: Política | C6: 10 | D6: 6 | E6: =C6+D6 | F6: 6 | G6: 1 | H6: =SUMIFS('Corpus - oraciones'!$AD$5:$AD$600,'Corpus - oraciones'!$C$5:$C$600,A6,'Corpus - oraciones'!$D$5:$D$600,B6) | I6: =IFERROR(H6/E6,0) | J6: Pendiente | K6: Subset curado de las 500 oraciones del corpus original (sub-temas Transición/EEUU/Reformas/Seguridad, sin Terremoto).
A7: El Espectador | B7: Política | C7: 20 | D7: 0 | E7: =C7+D7 | F7: 4 | G7: 0 | H7: =SUMIFS('Corpus - oraciones'!$AD$5:$AD$600,'Corpus - oraciones'!$C$5:$C$600,A7,'Corpus - oraciones'!$D$5:$D$600,B7) | I7: =IFERROR(H7/E7,0) | J7: Pendiente | K7: Subset curado de las 500 oraciones originales (Transición/EEUU/Reformas/Seguridad, sin Terremoto).
A8: La Silla Vacía | B8: Política | C8: 2 | D8: 9 | E8: =C8+D8 | F8: 2 | G8: 9 | H8: =SUMIFS('Corpus - oraciones'!$AD$5:$AD$600,'Corpus - oraciones'!$C$5:$C$600,A8,'Corpus - oraciones'!$D$5:$D$600,B8) | I8: =IFERROR(H8/E8,0) | J8: Pendiente | K8: Subset curado de las 500 oraciones del corpus original (sub-temas Transición/EEUU/Reformas/Seguridad, sin Terremoto).
A9: Semana | B9: Política | C9: 30 | D9: 10 | E9: =C9+D9 | F9: 3 | G9: 1 | H9: =SUMIFS('Corpus - oraciones'!$AD$5:$AD$600,'Corpus - oraciones'!$C$5:$C$600,A9,'Corpus - oraciones'!$D$5:$D$600,B9) | I9: =IFERROR(H9/E9,0) | J9: Pendiente | K9: Subset curado de las 500 oraciones del corpus original (sub-temas Transición/EEUU/Reformas/Seguridad, sin Terremoto).
A10: Infobae Colombia | B10: Economía y negocios | C10: 20 | D10: 0 | E10: =C10+D10 | F10: 3 | G10: 0 | H10: =SUMIFS('Corpus - oraciones'!$AD$5:$AD$600,'Corpus - oraciones'!$C$5:$C$600,A10,'Corpus - oraciones'!$D$5:$D$600,B10) | I10: =IFERROR(H10/E10,0) | J10: Pendiente
A11: El Tiempo | B11: Economía y negocios | C11: 14 | D11: 6 | E11: =C11+D11 | F11: 2 | G11: 1 | H11: =SUMIFS('Corpus - oraciones'!$AD$5:$AD$600,'Corpus - oraciones'!$C$5:$C$600,A11,'Corpus - oraciones'!$D$5:$D$600,B11) | I11: =IFERROR(H11/E11,0) | J11: Pendiente
A12: El Espectador | B12: Economía y negocios | C12: 6 | D12: 14 | E12: =C12+D12 | F12: 1 | G12: 1 | H12: =SUMIFS('Corpus - oraciones'!$AD$5:$AD$600,'Corpus - oraciones'!$C$5:$C$600,A12,'Corpus - oraciones'!$D$5:$D$600,B12) | I12: =IFERROR(H12/E12,0) | J12: Pendiente
A13: La Silla Vacía | B13: Economía y negocios | C13: 8 | D13: 12 | E13: =C13+D13 | F13: 2 | G13: 1 | H13: =SUMIFS('Corpus - oraciones'!$AD$5:$AD$600,'Corpus - oraciones'!$C$5:$C$600,A13,'Corpus - oraciones'!$D$5:$D$600,B13) | I13: =IFERROR(H13/E13,0) | J13: Pendiente
A14: Semana | B14: Economía y negocios | C14: 10 | D14: 10 | E14: =C14+D14 | F14: 2 | G14: 1 | H14: =SUMIFS('Corpus - oraciones'!$AD$5:$AD$600,'Corpus - oraciones'!$C$5:$C$600,A14,'Corpus - oraciones'!$D$5:$D$600,B14) | I14: =IFERROR(H14/E14,0) | J14: Pendiente
A15: Infobae Colombia | B15: Salud | C15: 20 | D15: 0 | E15: =C15+D15 | F15: 3 | G15: 0 | H15: =SUMIFS('Corpus - oraciones'!$AD$5:$AD$600,'Corpus - oraciones'!$C$5:$C$600,A15,'Corpus - oraciones'!$D$5:$D$600,B15) | I15: =IFERROR(H15/E15,0) | J15: Pendiente
A16: El Tiempo | B16: Salud | C16: 14 | D16: 6 | E16: =C16+D16 | F16: 2 | G16: 1 | H16: =SUMIFS('Corpus - oraciones'!$AD$5:$AD$600,'Corpus - oraciones'!$C$5:$C$600,A16,'Corpus - oraciones'!$D$5:$D$600,B16) | I16: =IFERROR(H16/E16,0) | J16: Pendiente
A17: El Espectador | B17: Salud | C17: 6 | D17: 14 | E17: =C17+D17 | F17: 1 | G17: 1 | H17: =SUMIFS('Corpus - oraciones'!$AD$5:$AD$600,'Corpus - oraciones'!$C$5:$C$600,A17,'Corpus - oraciones'!$D$5:$D$600,B17) | I17: =IFERROR(H17/E17,0) | J17: Pendiente
A18: La Silla Vacía | B18: Salud | C18: 8 | D18: 12 | E18: =C18+D18 | F18: 1 | G18: 1 | H18: =SUMIFS('Corpus - oraciones'!$AD$5:$AD$600,'Corpus - oraciones'!$C$5:$C$600,A18,'Corpus - oraciones'!$D$5:$D$600,B18) | I18: =IFERROR(H18/E18,0) | J18: Pendiente
A19: Semana | B19: Salud | C19: 10 | D19: 10 | E19: =C19+D19 | F19: 1 | G19: 1 | H19: =SUMIFS('Corpus - oraciones'!$AD$5:$AD$600,'Corpus - oraciones'!$C$5:$C$600,A19,'Corpus - oraciones'!$D$5:$D$600,B19) | I19: =IFERROR(H19/E19,0) | J19: Pendiente
A20: Infobae Colombia | B20: Medio ambiente | C20: 20 | D20: 0 | E20: =C20+D20 | F20: 2 | G20: 0 | H20: =SUMIFS('Corpus - oraciones'!$AD$5:$AD$600,'Corpus - oraciones'!$C$5:$C$600,A20,'Corpus - oraciones'!$D$5:$D$600,B20) | I20: =IFERROR(H20/E20,0) | J20: Pendiente
A21: El Tiempo | B21: Medio ambiente | C21: 14 | D21: 6 | E21: =C21+D21 | F21: 3 | G21: 1 | H21: =SUMIFS('Corpus - oraciones'!$AD$5:$AD$600,'Corpus - oraciones'!$C$5:$C$600,A21,'Corpus - oraciones'!$D$5:$D$600,B21) | I21: =IFERROR(H21/E21,0) | J21: Pendiente
A22: El Espectador | B22: Medio ambiente | C22: 20 | D22: 0 | E22: =C22+D22 | F22: 2 | G22: 0 | H22: =SUMIFS('Corpus - oraciones'!$AD$5:$AD$600,'Corpus - oraciones'!$C$5:$C$600,A22,'Corpus - oraciones'!$D$5:$D$600,B22) | I22: =IFERROR(H22/E22,0) | J22: Pendiente | K22: El artículo de análisis sobre fracking resultó ser nota explicativa neutral (auditoría): se clasificó como 'Noticia dura'; por eso la celda quedó 20 dura / 0 opinión.
A23: La Silla Vacía | B23: Medio ambiente | C23: 8 | D23: 12 | E23: =C23+D23 | F23: 2 | G23: 2 | H23: =SUMIFS('Corpus - oraciones'!$AD$5:$AD$600,'Corpus - oraciones'!$C$5:$C$600,A23,'Corpus - oraciones'!$D$5:$D$600,B23) | I23: =IFERROR(H23/E23,0) | J23: Pendiente
A24: Semana | B24: Medio ambiente | C24: 10 | D24: 10 | E24: =C24+D24 | F24: 1 | G24: 1 | H24: =SUMIFS('Corpus - oraciones'!$AD$5:$AD$600,'Corpus - oraciones'!$C$5:$C$600,A24,'Corpus - oraciones'!$D$5:$D$600,B24) | I24: =IFERROR(H24/E24,0) | J24: Pendiente
A25: Infobae Colombia | B25: Deportes | C25: 25 | D25: 0 | E25: =C25+D25 | F25: 5 | G25: 0 | H25: =SUMIFS('Corpus - oraciones'!$AD$5:$AD$600,'Corpus - oraciones'!$C$5:$C$600,A25,'Corpus - oraciones'!$D$5:$D$600,B25) | I25: =IFERROR(H25/E25,0) | J25: Pendiente
A26: El Tiempo | B26: Deportes | C26: 17 | D26: 14 | E26: =C26+D26 | F26: 3 | G26: 2 | H26: =SUMIFS('Corpus - oraciones'!$AD$5:$AD$600,'Corpus - oraciones'!$C$5:$C$600,A26,'Corpus - oraciones'!$D$5:$D$600,B26) | I26: =IFERROR(H26/E26,0) | J26: Pendiente
A27: El Espectador | B27: Deportes | C27: 8 | D27: 23 | E27: =C27+D27 | F27: 2 | G27: 3 | H27: =SUMIFS('Corpus - oraciones'!$AD$5:$AD$600,'Corpus - oraciones'!$C$5:$C$600,A27,'Corpus - oraciones'!$D$5:$D$600,B27) | I27: =IFERROR(H27/E27,0) | J27: Pendiente
A28: La Silla Vacía | B28: Deportes | C28: 0 | D28: 0 | E28: =C28+D28 | F28: 0 | G28: 0 | H28: =SUMIFS('Corpus - oraciones'!$AD$5:$AD$600,'Corpus - oraciones'!$C$5:$C$600,A28,'Corpus - oraciones'!$D$5:$D$600,B28) | I28: =IFERROR(H28/E28,0) | J28: Pendiente | K28: La Silla Vacía no tiene cobertura deportiva activa 2025-2026 (verificado): su cuota se redistribuyó entre los otros 4 medios.
A29: Semana | B29: Deportes | C29: 13 | D29: 0 | E29: =C29+D29 | F29: 2 | G29: 0 | H29: =SUMIFS('Corpus - oraciones'!$AD$5:$AD$600,'Corpus - oraciones'!$C$5:$C$600,A29,'Corpus - oraciones'!$D$5:$D$600,B29) | I29: =IFERROR(H29/E29,0) | J29: Pendiente | K29: Semana no tiene columnistas de opinión deportiva (verificado): su cuota de opinión se redistribuyó a El Tiempo y El Espectador.
A30: TOTAL | C30: =SUM(C5:C29) | D30: =SUM(D5:D29) | E30: =SUM(E5:E29) | H30: =SUM(H5:H29) | I30: =IFERROR(H30/E30,0)

Sheet Resumen
A1: Resumen por medio y por dominio — corpus v2
A3: Por medio
A4: Medio | B4: Objetivo total | C4: Oraciones anotadas | D4: % avance
A5: Infobae Colombia | B5: =SUMIF('Grid de recoleccion'!A:A,A5,'Grid de recoleccion'!E:E) | C5: =SUMIF('Grid de recoleccion'!A:A,A5,'Grid de recoleccion'!H:H) | D5: =IFERROR(C5/B5,0)
A6: El Tiempo | B6: =SUMIF('Grid de recoleccion'!A:A,A6,'Grid de recoleccion'!E:E) | C6: =SUMIF('Grid de recoleccion'!A:A,A6,'Grid de recoleccion'!H:H) | D6: =IFERROR(C6/B6,0)
A7: El Espectador | B7: =SUMIF('Grid de recoleccion'!A:A,A7,'Grid de recoleccion'!E:E) | C7: =SUMIF('Grid de recoleccion'!A:A,A7,'Grid de recoleccion'!H:H) | D7: =IFERROR(C7/B7,0)
A8: La Silla Vacía | B8: =SUMIF('Grid de recoleccion'!A:A,A8,'Grid de recoleccion'!E:E) | C8: =SUMIF('Grid de recoleccion'!A:A,A8,'Grid de recoleccion'!H:H) | D8: =IFERROR(C8/B8,0)
A9: Semana | B9: =SUMIF('Grid de recoleccion'!A:A,A9,'Grid de recoleccion'!E:E) | C9: =SUMIF('Grid de recoleccion'!A:A,A9,'Grid de recoleccion'!H:H) | D9: =IFERROR(C9/B9,0)
A10: TOTAL | B10: =SUM(B5:B9) | C10: =SUM(C5:C9) | D10: =IFERROR(C10/B10,0)
A13: Por dominio
A14: Dominio | B14: Objetivo total | C14: Oraciones anotadas | D14: % avance
A15: Política | B15: =SUMIF('Grid de recoleccion'!B:B,A15,'Grid de recoleccion'!E:E) | C15: =SUMIF('Grid de recoleccion'!B:B,A15,'Grid de recoleccion'!H:H) | D15: =IFERROR(C15/B15,0)
A16: Economía y negocios | B16: =SUMIF('Grid de recoleccion'!B:B,A16,'Grid de recoleccion'!E:E) | C16: =SUMIF('Grid de recoleccion'!B:B,A16,'Grid de recoleccion'!H:H) | D16: =IFERROR(C16/B16,0)
A17: Salud | B17: =SUMIF('Grid de recoleccion'!B:B,A17,'Grid de recoleccion'!E:E) | C17: =SUMIF('Grid de recoleccion'!B:B,A17,'Grid de recoleccion'!H:H) | D17: =IFERROR(C17/B17,0)
A18: Medio ambiente | B18: =SUMIF('Grid de recoleccion'!B:B,A18,'Grid de recoleccion'!E:E) | C18: =SUMIF('Grid de recoleccion'!B:B,A18,'Grid de recoleccion'!H:H) | D18: =IFERROR(C18/B18,0)
A19: Deportes | B19: =SUMIF('Grid de recoleccion'!B:B,A19,'Grid de recoleccion'!E:E) | C19: =SUMIF('Grid de recoleccion'!B:B,A19,'Grid de recoleccion'!H:H) | D19: =IFERROR(C19/B19,0)
A20: TOTAL | B20: =SUM(B15:B19) | C20: =SUM(C15:C19) | D20: =IFERROR(C20/B20,0)

Sheet Leyenda
A1: Cómo usar este archivo
A3: Qué es este archivo | B3: Corpus multi-dominio v2: 500 oraciones reales de 5 medios colombianos (Infobae Colombia, El Tiempo, El Espectador, La Silla Vacía, Semana) repartidas en 5 dominios de 100 oraciones cada uno: Política, Economía y negocios, Salud, Medio ambiente y Deportes. La recolección está cerrada y auditada; lo que falta es la ANOTACIÓN.
A4: Hoja 'Corpus - oraciones' | B4: Es la hoja de trabajo: una fila por oración, 500 filas (de la fila 5 a la 504). Las columnas en GRIS (A–I, más aux y url_fuente) vienen dadas y NO se editan. Las columnas en AMARILLO (J a AC) son las que llena el anotador: las 9 categorías con su span, direccion y actor_objetivo.
A5: Unidad de anotación | B5: La oración. Toda oración revisada recibe exactamente una fila, incluso si todas las categorías quedan en FALSE: las oraciones neutras son tan necesarias como las sesgadas, no se omiten.
A6: Esquema de anotación | B6: 9 categorías booleanas, cada una con su columna de span al lado (se llena solo si la categoría quedó en TRUE): 5 léxicas J1 (verbo_factivo, verbo_asertivo, palabra_subjetiva, hedge, etiqueta_valorativa) y 4 discursivas J2 (sensacionalismo, mind_reading, falta_atribucion, opinion_como_hecho). Se suman direccion (favorece / perjudica / neutral) y actor_objetivo (lista cerrada de 9 opciones, obligatorio si direccion no es neutral). En total, 11 campos por oración.
A7: Listas desplegables | B7: medio, tema, género, direccion y las 9 categorías booleanas tienen lista desplegable: seleccione siempre de la lista, no escriba a mano.
A8: Ejemplo de fila anotada | B8: Oración: «El Gobierno impuso la polémica reforma tributaria pese a las advertencias de los gremios, sabiendo que afectaría directamente a la clase media.» → tres mecanismos en la MISMA fila: palabra_subjetiva = TRUE con span «impuso»; etiqueta_valorativa = TRUE con span «polémica»; mind_reading = TRUE con span «sabiendo que afectaría directamente a la clase media». Las otras 6 categorías quedan en FALSE. direccion = perjudica y actor_objetivo = Gobierno / Ejecutivo. Las categorías no son excluyentes: se marcan todas las que apliquen, cada una con su propio span, y la oración sigue ocupando una sola fila.
A9: Ejemplo de oración neutral | B9: Oración: «El Banco de la República publicará el informe de inflación el próximo martes.» → las 9 categorías en FALSE, sin span, direccion = neutral y actor_objetivo vacío. La fila se conserva igual: las oraciones neutras son parte del corpus, no se omiten.
A10: Hoja 'Grid de recoleccion' | B10: Tablero de control por medio × dominio. 'Objetivo' = lo realmente recolectado (ya cerrado). 'Artículos de origen' indica de cuántos artículos distintos salieron esas oraciones. 'Oraciones ya anotadas' y el '% avance' se calculan solos: cuentan las oraciones que ya tienen 'direccion' llena, así que arrancan en 0% y llegan a 100% cuando se termina esa celda. Edite solo Estado (Pendiente / En progreso / Completo) y Notas.
A11: Hoja 'Resumen' | B11: Se calcula sola a partir del Grid: totales por medio y por dominio. Solo lectura.
A12: IDs | B12: articulo_id va de ART_001 a ART_089, ordenados por dominio → medio → género. oracion_id = articulo_id + _S## con numeración contigua dentro de cada artículo (S01, S02, ...). Un mismo articulo_id = un mismo artículo real (misma url_fuente).
A13: Contexto | B13: oracion_anterior y oracion_siguiente traen las oraciones vecinas reales del mismo artículo, para que el anotador juzgue en contexto. Están vacías cuando la oración es la primera o la última capturada del artículo.
A14: actor_objetivo (lista cerrada) | B14: Se llena SOLO si direccion != neutral; si direccion = neutral, déjelo vacío. Nueve opciones: Gobierno / Ejecutivo; Oposición / partidos políticos; Instituciones del Estado; Empresas y gremios; Sindicatos y organizaciones sociales; Ciudadanía afectada; Actores del deporte; Actor internacional; Otro / no identificable. Regla clave: anote el ROL institucional, no la persona (Petro como presidente → Gobierno / Ejecutivo; Néstor Lorenzo como DT → Actores del deporte).

Sheet Corpus - oraciones
A1: Corpus multi-dominio v2 — una fila por oración (esquema completo: 9 categorías léxico/discursivo)
A2: 500 oraciones reales de 5 medios colombianos en 5 dominios (Política, Economía y negocios, Salud, Medio ambiente, Deportes), 100 por dominio. Datos desde la fila 5. GRIS = viene dado, no se toca. AMARILLO = lo llena el anotador (columnas J a AC). La columna AD es auxiliar y alimenta el Grid; la AE trae la URL del artículo original.
A4: articulo_id | B4: oracion_id | C4: medio | D4: tema | E4: género (dura/opinión) | F4: fecha_ publicación | G4: oracion_texto | H4: oracion_anterior | I4: oracion_siguiente | J4: verbo_factivo (J1) | K4: verbo_factivo_span | L4: verbo_asertivo (J1) | M4: verbo_asertivo_span | N4: palabra_subjetiva (J1) | O4: palabra_subjetiva_span | P4: hedge (J1) | Q4: hedge_span | R4: etiqueta_valorativa (J1) | S4: etiqueta_valorativa_span | T4: sensacionalismo (J2) | U4: sensacionalismo_span | V4: mind_reading (J2) | W4: mind_reading_span | X4: falta_atribucion (J2) | Y4: falta_atribucion_span | Z4: opinion_como_hecho (J2) | AA4: opinion_como_hecho_span | AB4: direccion | AC4: actor_objetivo | AD4: aux: primera fila de la oración (no editar) | AE4: url_fuente
A5: ART_001 | B5: ART_001_S01 | C5: Infobae Colombia | D5: Política | E5: Noticia dura | F5: Fri, 04 Sep 2026 18:20:11 +0000 | G5: La Alianza Verde salió a responder a las expresiones del senador del Pacto Histórico David Racero contra la representante de su partido Catherine Juvinao durante la discusión del Presupuesto General de la Nación (PGN) 2027 en las comisiones económicas del Congreso de la República. | I5: La colectividad “rechaza contundentemente la violencia política, verbal y simbólica” de la que, según afirma, ha sido víctima la congresista por parte del legislador del Pacto Histórico. | AD5: =IF(AND(COUNTIF($B$5:B5,B5)=1,$B5<>"",$AB5<>""),1,0) | AE5: https://www.infobae.com/colombia/2026/09/04/alianza-verde-critico-a-david-racero-por-llamar-lavaperros-a-catherine-juvinao-durante-la-discusion-del-presupuesto-general-de-la-nacion-violencia-politica-verbal-y-simbolica/
A6: ART_001 | B6: ART_001_S02 | C6: Infobae Colombia | D6: Política | E6: Noticia dura | F6: Fri, 04 Sep 2026 18:20:11 +0000 | G6: La colectividad “rechaza contundentemente la violencia política, verbal y simbólica” de la que, según afirma, ha sido víctima la congresista por parte del legislador del Pacto Histórico. | H6: La Alianza Verde salió a responder a las expresiones del senador del Pacto Histórico David Racero contra la representante de su partido Catherine Juvinao durante la discusión del Presupuesto General de la Nación (PGN) 2027 en las comisiones económicas del Congreso de la República. | AD6: =IF(AND(COUNTIF($B$5:B6,B6)=1,$B6<>"",$AB6<>""),1,0) | AE6: https://www.infobae.com/colombia/2026/09/04/alianza-verde-critico-a-david-racero-por-llamar-lavaperros-a-catherine-juvinao-durante-la-discusion-del-presupuesto-general-de-la-nacion-violencia-politica-verbal-y-simbolica/
A7: ART_002 | B7: ART_002_S01 | C7: Infobae Colombia | D7: Política | E7: Noticia dura | F7: Fri, 04 Sep 2026 02:29:45 +0000 | G7: Ni la Presidencia de la República, ejercida por Abelardo de la Espriella, ni el Ministerio de Defensa, ni la fuerza pública, están autorizadas para ejecutar operaciones aéreas ofensivas en zonas donde se sospeche que hay presencia de niños, niñas y adolescentes reclutados por organizaciones criminales. | AD7: =IF(AND(COUNTIF($B$5:B7,B7)=1,$B7<>"",$AB7<>""),1,0) | AE7: https://www.infobae.com/colombia/2026/09/04/accionante-que-logro-que-un-juzgado-frenara-bombardeos-por-presencia-de-menores-explico-el-alcance-de-su-tutela-se-deben-proteger/
A8: ART_003 | B8: ART_003_S01 | C8: Infobae Colombia | D8: Política | E8: Noticia dura | F8: Sat, 05 Sep 2026 23:40:04 +0000 | G8: Tras el ataque terrorista que perpetró el Ejército de Liberación Nacional (ELN) el 4 de septiembre contra el Cantón Militar El Trapiche, ubicado en Ocaña, Norte de Santander, se llevó a cabo un consejo de seguridad extraordinario para atender la situación de orden público. | I8: El atentado y los combates que se presentaron posteriormente dejaron tres militares asesinados: el capitán Marco David Pirajón Montezuma y los soldados profesionales Joel Alberto Jiménez Jaramillo y Jhon Carlo Marrugo Manjarrez. | AD8: =IF(AND(COUNTIF($B$5:B8,B8)=1,$B8<>"",$AB8<>""),1,0) | AE8: https://www.infobae.com/colombia/2026/09/05/toman-medidas-para-reforzar-la-seguridad-en-ocana-y-norte-de-santander-tras-atentado-del-eln-activaran-la-campana-militar-y-policial-esparta/
A9: ART_003 | B9: ART_003_S02 | C9: Infobae Colombia | D9: Política | E9: Noticia dura | F9: Sat, 05 Sep 2026 23:40:04 +0000 | G9: El atentado y los combates que se presentaron posteriormente dejaron tres militares asesinados: el capitán Marco David Pirajón Montezuma y los soldados profesionales Joel Alberto Jiménez Jaramillo y Jhon Carlo Marrugo Manjarrez. | H9: Tras el ataque terrorista que perpetró el Ejército de Liberación Nacional (ELN) el 4 de septiembre contra el Cantón Militar El Trapiche, ubicado en Ocaña, Norte de Santander, se llevó a cabo un consejo de seguridad extraordinario para atender la situación de orden público. | I9: Ante la gravedad de estos hechos, se establecieron nuevas medidas para reforzar la seguridad y el control territorial en Ocaña y en la región del Catatumbo. | AD9: =IF(AND(COUNTIF($B$5:B9,B9)=1,$B9<>"",$AB9<>""),1,0) | AE9: https://www.infobae.com/colombia/2026/09/05/toman-medidas-para-reforzar-la-seguridad-en-ocana-y-norte-de-santander-tras-atentado-del-eln-activaran-la-campana-militar-y-policial-esparta/
A10: ART_003 | B10: ART_003_S03 | C10: Infobae Colombia | D10: Política | E10: Noticia dura | F10: Sat, 05 Sep 2026 23:40:04 +0000 | G10: Ante la gravedad de estos hechos, se establecieron nuevas medidas para reforzar la seguridad y el control territorial en Ocaña y en la región del Catatumbo. | H10: El atentado y los combates que se presentaron posteriormente dejaron tres militares asesinados: el capitán Marco David Pirajón Montezuma y los soldados profesionales Joel Alberto Jiménez Jaramillo y Jhon Carlo Marrugo Manjarrez. | I10: Durante la reunión, en la que estuvo el Ministerio de Defensa Nacional, la cúpula militar y de la Policía Nacional, y el gobernador de Norte de Santander, William Villamizar Laguado, el Gobierno del presidente Abelardo de la Espriella y las autoridades concertaron hacer una reestructuración y activación de la campaña militar y policial Esparta, con sede en Ocaña, para articular capacidades de las Fuerzas Militares y la Policía Nacional frente a las estructuras criminales que operan en la zona. | AD10: =IF(AND(COUNTIF($B$5:B10,B10)=1,$B10<>"",$AB10<>""),1,0) | AE10: https://www.infobae.com/colombia/2026/09/05/toman-medidas-para-reforzar-la-seguridad-en-ocana-y-norte-de-santander-tras-atentado-del-eln-activaran-la-campana-militar-y-policial-esparta/
A11: ART_003 | B11: ART_003_S04 | C11: Infobae Colombia | D11: Política | E11: Noticia dura | F11: Sat, 05 Sep 2026 23:40:04 +0000 | G11: Durante la reunión, en la que estuvo el Ministerio de Defensa Nacional, la cúpula militar y de la Policía Nacional, y el gobernador de Norte de Santander, William Villamizar Laguado, el Gobierno del presidente Abelardo de la Espriella y las autoridades concertaron hacer una reestructuración y activación de la campaña militar y policial Esparta, con sede en Ocaña, para articular capacidades de las Fuerzas Militares y la Policía Nacional frente a las estructuras criminales que operan en la zona. | H11: Ante la gravedad de estos hechos, se establecieron nuevas medidas para reforzar la seguridad y el control territorial en Ocaña y en la región del Catatumbo. | I11: “Se reforzarán los corredores de movilidad ilegal, las capacidades de inteligencia y la coordinación con la @FiscaliaCol para identificar, capturar y judicializar a los responsables. | AD11: =IF(AND(COUNTIF($B$5:B11,B11)=1,$B11<>"",$AB11<>""),1,0) | AE11: https://www.infobae.com/colombia/2026/09/05/toman-medidas-para-reforzar-la-seguridad-en-ocana-y-norte-de-santander-tras-atentado-del-eln-activaran-la-campana-militar-y-policial-esparta/
A12: ART_003 | B12: ART_003_S05 | C12: Infobae Colombia | D12: Política | E12: Noticia dura | F12: Sat, 05 Sep 2026 23:40:04 +0000 | G12: “Se reforzarán los corredores de movilidad ilegal, las capacidades de inteligencia y la coordinación con la @FiscaliaCol para identificar, capturar y judicializar a los responsables. | H12: Durante la reunión, en la que estuvo el Ministerio de Defensa Nacional, la cúpula militar y de la Policía Nacional, y el gobernador de Norte de Santander, William Villamizar Laguado, el Gobierno del presidente Abelardo de la Espriella y las autoridades concertaron hacer una reestructuración y activación de la campaña militar y policial Esparta, con sede en Ocaña, para articular capacidades de las Fuerzas Militares y la Policía Nacional frente a las estructuras criminales que operan en la zona. | I12: Las @FuerzasMilCol y la @PoliciaColombia mantienen desplegadas todas sus capacidades para proteger a la población y enfrentar con contundencia a quienes atenten contra la seguridad del #Catatumbo”, indicaron las Fuerzas Militares en X. | AD12: =IF(AND(COUNTIF($B$5:B12,B12)=1,$B12<>"",$AB12<>""),1,0) | AE12: https://www.infobae.com/colombia/2026/09/05/toman-medidas-para-reforzar-la-seguridad-en-ocana-y-norte-de-santander-tras-atentado-del-eln-activaran-la-campana-militar-y-policial-esparta/
A13: ART_003 | B13: ART_003_S06 | C13: Infobae Colombia | D13: Política | E13: Noticia dura | F13: Sat, 05 Sep 2026 23:40:04 +0000 | G13: Las @FuerzasMilCol y la @PoliciaColombia mantienen desplegadas todas sus capacidades para proteger a la población y enfrentar con contundencia a quienes atenten contra la seguridad del #Catatumbo”, indicaron las Fuerzas Militares en X. | H13: “Se reforzarán los corredores de movilidad ilegal, las capacidades de inteligencia y la coordinación con la @FiscaliaCol para identificar, capturar y judicializar a los responsables. | AD13: =IF(AND(COUNTIF($B$5:B13,B13)=1,$B13<>"",$AB13<>""),1,0) | AE13: https://www.infobae.com/colombia/2026/09/05/toman-medidas-para-reforzar-la-seguridad-en-ocana-y-norte-de-santander-tras-atentado-del-eln-activaran-la-campana-militar-y-policial-esparta/
A14: ART_004 | B14: ART_004_S01 | C14: Infobae Colombia | D14: Política | E14: Noticia dura | F14: 2026-08-04T18:45:15Z | G14: El director de la Dirección de Impuestos y Aduanas Nacionales (Dian) Carlos Betancourt sostuvo que el aumento de aranceles de Estados Unidos a Colombia, que pasó de 10% a 12,5%, fue una decisión unilateral del gobierno de Donald Trump y no una consecuencia de incumplimientos del Estado colombiano, en un contexto marcado por la guerra comercial con China, la estrategia de Washington para fortalecer sus exportaciones y factores geopolíticos. | AD14: =IF(AND(COUNTIF($B$5:B14,B14)=1,$B14<>"",$AB14<>""),1,0) | AE14: https://www.infobae.com/colombia/2026/08/04/el-director-de-la-dian-atribuyo-a-donald-trump-la-subida-de-aranceles-de-estados-unidos-a-colombia-es-una-decision-unilateral/
A15: ART_005 | B15: ART_005_S01 | C15: Infobae Colombia | D15: Política | E15: Noticia dura | F15: 2026-07-23T23:10:16Z | G15: La administración del presidente Donald Trump confirmó el jueves 23 de julio de 2026 un nuevo paquete de aranceles para las importaciones provenientes de decenas de países, entre ellos Colombia, decisión que fija un gravamen del 12,5% para los productos colombianos que ingresen al mercado estadounidense. | AD15: =IF(AND(COUNTIF($B$5:B15,B15)=1,$B15<>"",$AB15<>""),1,0) | AE15: https://www.infobae.com/colombia/2026/07/23/estados-unidos-endurecio-los-aranceles-para-colombia-exportaciones-pagaran-un-gravamen-del-125/
A16: ART_006 | B16: ART_006_S01 | C16: Infobae Colombia | D16: Política | E16: Noticia dura | F16: 2026-09-07T01:06:46Z | G16: El exministro de Hacienda José Antonio Ocampo se refirió al aval que le dio la Corte Constitucional a la reforma pensional, principalmente, sobre un cambio que considera central: Colpensiones dejaría de competir con el ahorro individual para operar en un esquema complementario. | I16: El exfuncionario dijo que el sistema tendrá costos altos desde 2067, cuando se agoten los recursos de un fondo especial. | AD16: =IF(AND(COUNTIF($B$5:B16,B16)=1,$B16<>"",$AB16<>""),1,0) | AE16: https://www.infobae.com/colombia/2026/09/07/reforma-pensional-confirman-en-que-ano-se-acabara-el-ahorro-de-los-trabajadores-colombianos-y-cuando-colapsara-colpensiones/
A17: ART_006 | B17: ART_006_S02 | C17: Infobae Colombia | D17: Política | E17: Noticia dura | F17: 2026-09-07T01:06:46Z | G17: El exfuncionario dijo que el sistema tendrá costos altos desde 2067, cuando se agoten los recursos de un fondo especial. | H17: El exministro de Hacienda José Antonio Ocampo se refirió al aval que le dio la Corte Constitucional a la reforma pensional, principalmente, sobre un cambio que considera central: Colpensiones dejaría de competir con el ahorro individual para operar en un esquema complementario. | AD17: =IF(AND(COUNTIF($B$5:B17,B17)=1,$B17<>"",$AB17<>""),1,0) | AE17: https://www.infobae.com/colombia/2026/09/07/reforma-pensional-confirman-en-que-ano-se-acabara-el-ahorro-de-los-trabajadores-colombianos-y-cuando-colapsara-colpensiones/
A18: ART_007 | B18: ART_007_S01 | C18: El Tiempo | D18: Política | E18: Noticia dura | F18: 2026-09-04T16:36:43-05:00 | G18: La decisión de la Alianza Verde de declararse como partido independiente al gobierno de Abelardo De La Espriella ha generado polémica. | AD18: =IF(AND(COUNTIF($B$5:B18,B18)=1,$B18<>"",$AB18<>""),1,0) | AE18: https://www.eltiempo.com/politica/partidos-politicos/las-movidas-detras-de-la-declaratoria-de-la-alianza-verde-como-partido-independiente-al-gobierno-de-abelardo-de-la-espriella-3583710
A19: ART_008 | B19: ART_008_S01 | C19: El Tiempo | D19: Política | E19: Noticia dura | F19: 2026-09-04T10:51:14-05:00 | G19: El presidente Abelardo De La Espriella y su cúpula militar confirmaron en Riohacha la muerte de Naín Andrés Pérez Toncel, alias 'Bendito menor', señalado cabecilla de las Autodefensas Conquistadoras de la Sierra Nevada, durante un operativo de la Policía denominado 'Centinela de la patria'. | I19: Según detalló el mandatario, junto al cabecilla de las Acsn también murieron su pareja, Rosa Angélica Tarazona, alias ‘La Bebecita’, y dos escoltas. | AD19: =IF(AND(COUNTIF($B$5:B19,B19)=1,$B19<>"",$AB19<>""),1,0) | AE19: https://www.eltiempo.com/politica/abelardo-de-la-espriella/presidente-abelardo-de-la-espriella-y-su-contundente-frase-tras-la-muerte-de-bendito-menor-este-miserable-ahora-esta-a-buen-recaudo-del-infierno-3583557
A20: ART_008 | B20: ART_008_S02 | C20: El Tiempo | D20: Política | E20: Noticia dura | F20: 2026-09-04T10:51:14-05:00 | G20: Según detalló el mandatario, junto al cabecilla de las Acsn también murieron su pareja, Rosa Angélica Tarazona, alias ‘La Bebecita’, y dos escoltas. | H20: El presidente Abelardo De La Espriella y su cúpula militar confirmaron en Riohacha la muerte de Naín Andrés Pérez Toncel, alias 'Bendito menor', señalado cabecilla de las Autodefensas Conquistadoras de la Sierra Nevada, durante un operativo de la Policía denominado 'Centinela de la patria'. | AD20: =IF(AND(COUNTIF($B$5:B20,B20)=1,$B20<>"",$AB20<>""),1,0) | AE20: https://www.eltiempo.com/politica/abelardo-de-la-espriella/presidente-abelardo-de-la-espriella-y-su-contundente-frase-tras-la-muerte-de-bendito-menor-este-miserable-ahora-esta-a-buen-recaudo-del-infierno-3583557
A21: ART_009 | B21: ART_009_S01 | C21: El Tiempo | D21: Política | E21: Noticia dura | F21: 2026-09-04T07:46:26-05:00 | G21: Washington y Nueva York serán los dos escenarios que marcarán el ritmo de la política exterior del gobierno de Abelardo De La Espriella. | AD21: =IF(AND(COUNTIF($B$5:B21,B21)=1,$B21<>"",$AB21<>""),1,0) | AE21: https://www.eltiempo.com/politica/gobierno/embajadores-ante-ee-uu-y-naciones-unidas-se-preparan-para-asumir-los-destinos-clave-para-la-diplomacia-del-presidente-abelardo-de-la-espriella-3583494
A22: ART_010 | B22: ART_010_S01 | C22: El Tiempo | D22: Política | E22: Noticia dura | F22: 2026-09-04T16:28:46-05:00 | G22: El presidente de Estados Unidos, Donald Trump, afirmó este viernes que México tiene poco que ofrecer a su país más allá de "tamales picantes y tomates", aunque descartó interrumpir la relación comercial bilateral y destacó la buena sintonía que mantiene con la presidenta mexicana, Claudia Sheinbaum. | I22: Trump hizo estas declaraciones en el Despacho Oval al ser consultado por periodistas sobre su amenaza de suspender el comercio con países que mantienen un superávit comercial frente a Estados Unidos. | AD22: =IF(AND(COUNTIF($B$5:B22,B22)=1,$B22<>"",$AB22<>""),1,0) | AE22: https://www.eltiempo.com/mundo/eeuu-y-canada/tamales-picantes-y-tomates-estas-fueron-las-polemicas-declaraciones-de-trump-sobre-la-relacion-comercial-entre-mexico-y-estados-unidos-3583705
A23: ART_010 | B23: ART_010_S02 | C23: El Tiempo | D23: Política | E23: Noticia dura | F23: 2026-09-04T16:28:46-05:00 | G23: Trump hizo estas declaraciones en el Despacho Oval al ser consultado por periodistas sobre su amenaza de suspender el comercio con países que mantienen un superávit comercial frente a Estados Unidos. | H23: El presidente de Estados Unidos, Donald Trump, afirmó este viernes que México tiene poco que ofrecer a su país más allá de "tamales picantes y tomates", aunque descartó interrumpir la relación comercial bilateral y destacó la buena sintonía que mantiene con la presidenta mexicana, Claudia Sheinbaum. | AD23: =IF(AND(COUNTIF($B$5:B23,B23)=1,$B23<>"",$AB23<>""),1,0) | AE23: https://www.eltiempo.com/mundo/eeuu-y-canada/tamales-picantes-y-tomates-estas-fueron-las-polemicas-declaraciones-de-trump-sobre-la-relacion-comercial-entre-mexico-y-estados-unidos-3583705
A24: ART_011 | B24: ART_011_S01 | C24: El Tiempo | D24: Política | E24: Noticia dura | F24: 2026-09-04T16:23:07-05:00 | G24: Después de estar al frente de la Décima Primera Brigada, el brigadier general Óscar del Cristo Díaz Montiel asumió una nueva responsabilidad dentro de la estructura del Ejército. | I24: El oficial fue designado comandante del Comando de Educación y Doctrina (Cedoc), desde donde tendrá a cargo los lineamientos para la formación, instrucción y entrenamiento de los integrantes de la Fuerza. | AD24: =IF(AND(COUNTIF($B$5:B24,B24)=1,$B24<>"",$AB24<>""),1,0) | AE24: https://www.eltiempo.com/justicia/conflicto-y-narcotrafico/general-oscar-diaz-montiel-asume-el-comando-de-educacion-y-doctrina-del-ejercito-3583704
A25: ART_011 | B25: ART_011_S02 | C25: El Tiempo | D25: Política | E25: Noticia dura | F25: 2026-09-04T16:23:07-05:00 | G25: El oficial fue designado comandante del Comando de Educación y Doctrina (Cedoc), desde donde tendrá a cargo los lineamientos para la formación, instrucción y entrenamiento de los integrantes de la Fuerza. | H25: Después de estar al frente de la Décima Primera Brigada, el brigadier general Óscar del Cristo Díaz Montiel asumió una nueva responsabilidad dentro de la estructura del Ejército. | AD25: =IF(AND(COUNTIF($B$5:B25,B25)=1,$B25<>"",$AB25<>""),1,0) | AE25: https://www.eltiempo.com/justicia/conflicto-y-narcotrafico/general-oscar-diaz-montiel-asume-el-comando-de-educacion-y-doctrina-del-ejercito-3583704
A26: ART_012 | B26: ART_012_S01 | C26: El Tiempo | D26: Política | E26: Noticia dura | F26: 2026-09-05T01:05:59-05:00 | G26: Llegar a la edad de pensión no significa automáticamente que una persona vaya a recibir una mesada mensual. | I26: Para pensionarse también debe cumplir determinadas condiciones, que dependen del régimen al que esté afiliado. | AD26: =IF(AND(COUNTIF($B$5:B26,B26)=1,$B26<>"",$AB26<>""),1,0) | AE26: https://www.eltiempo.com/economia/finanzas-personales/que-pasa-con-su-dinero-si-no-alcanza-a-cumplir-las-semanas-necesarias-para-pensionarse-consulte-que-hacer-si-esta-en-porvenir-o-colpensiones-3583613
A27: ART_012 | B27: ART_012_S02 | C27: El Tiempo | D27: Política | E27: Noticia dura | F27: 2026-09-05T01:05:59-05:00 | G27: Para pensionarse también debe cumplir determinadas condiciones, que dependen del régimen al que esté afiliado. | H27: Llegar a la edad de pensión no significa automáticamente que una persona vaya a recibir una mesada mensual. | AD27: =IF(AND(COUNTIF($B$5:B27,B27)=1,$B27<>"",$AB27<>""),1,0) | AE27: https://www.eltiempo.com/economia/finanzas-personales/que-pasa-con-su-dinero-si-no-alcanza-a-cumplir-las-semanas-necesarias-para-pensionarse-consulte-que-hacer-si-esta-en-porvenir-o-colpensiones-3583613
A28: ART_013 | B28: ART_013_S01 | C28: El Tiempo | D28: Política | E28: Opinión-análisis | F28: 2026-05-16T23:45:00-05:00 | G28: Durante más de ocho meses de campaña política hemos visto un proselitismo ampliamente basado en las redes sociales, donde, por un lado, el gobierno de Gustavo Petro y sus bodegas interneteras han trabajado con vigor por su candidato, el comunista Iván Cepeda, y, por el otro, el aspirante ‘outsider’ Abelardo de la Espriella ha cabalgado sobre una poderosa y robusta red de decenas de miles de influenciadores, seguidores y replicadores de su mensaje en las redes sociales. | I28: Si los demás candidatos han quedado rezagados, ha sido en buena medida porque fueron incapaces de usar, con intensidad y eficacia, esas tecnologías. | AD28: =IF(AND(COUNTIF($B$5:B28,B28)=1,$B28<>"",$AB28<>""),1,0) | AE28: https://www.eltiempo.com/opinion/columnistas/una-batalla-sin-partidos-3556318
A29: ART_013 | B29: ART_013_S02 | C29: El Tiempo | D29: Política | E29: Opinión-análisis | F29: 2026-05-16T23:45:00-05:00 | G29: Si los demás candidatos han quedado rezagados, ha sido en buena medida porque fueron incapaces de usar, con intensidad y eficacia, esas tecnologías. | H29: Durante más de ocho meses de campaña política hemos visto un proselitismo ampliamente basado en las redes sociales, donde, por un lado, el gobierno de Gustavo Petro y sus bodegas interneteras han trabajado con vigor por su candidato, el comunista Iván Cepeda, y, por el otro, el aspirante ‘outsider’ Abelardo de la Espriella ha cabalgado sobre una poderosa y robusta red de decenas de miles de influenciadores, seguidores y replicadores de su mensaje en las redes sociales. | I29: Las redes seguirán jugando un papel clave en esta recta final. | AD29: =IF(AND(COUNTIF($B$5:B29,B29)=1,$B29<>"",$AB29<>""),1,0) | AE29: https://www.eltiempo.com/opinion/columnistas/una-batalla-sin-partidos-3556318
A30: ART_013 | B30: ART_013_S03 | C30: El Tiempo | D30: Política | E30: Opinión-análisis | F30: 2026-05-16T23:45:00-05:00 | G30: Las redes seguirán jugando un papel clave en esta recta final. | H30: Si los demás candidatos han quedado rezagados, ha sido en buena medida porque fueron incapaces de usar, con intensidad y eficacia, esas tecnologías. | I30: Pero ahora, a dos semanas de la primera vuelta y cinco de la segunda, la batalla electoral ha aterrizado en la cruda realidad de las calles de ciudades, y de pueblos medianos y pequeños. | AD30: =IF(AND(COUNTIF($B$5:B30,B30)=1,$B30<>"",$AB30<>""),1,0) | AE30: https://www.eltiempo.com/opinion/columnistas/una-batalla-sin-partidos-3556318
A31: ART_013 | B31: ART_013_S04 | C31: El Tiempo | D31: Política | E31: Opinión-análisis | F31: 2026-05-16T23:45:00-05:00 | G31: Pero ahora, a dos semanas de la primera vuelta y cinco de la segunda, la batalla electoral ha aterrizado en la cruda realidad de las calles de ciudades, y de pueblos medianos y pequeños. | H31: Las redes seguirán jugando un papel clave en esta recta final. | I31: La chequera del régimen petrista ha regado cientos de municipios con miles y miles de millones de pesos en contratos de obras y servicios, así como en órdenes de trabajo individuales. | AD31: =IF(AND(COUNTIF($B$5:B31,B31)=1,$B31<>"",$AB31<>""),1,0) | AE31: https://www.eltiempo.com/opinion/columnistas/una-batalla-sin-partidos-3556318
A32: ART_013 | B32: ART_013_S05 | C32: El Tiempo | D32: Política | E32: Opinión-análisis | F32: 2026-05-16T23:45:00-05:00 | G32: La chequera del régimen petrista ha regado cientos de municipios con miles y miles de millones de pesos en contratos de obras y servicios, así como en órdenes de trabajo individuales. | H32: Pero ahora, a dos semanas de la primera vuelta y cinco de la segunda, la batalla electoral ha aterrizado en la cruda realidad de las calles de ciudades, y de pueblos medianos y pequeños. | I32: A ello se suma el apoyo de las bandas armadas que saben que con Cepeda seguirían gozando de la escandalosa impunidad que Petro les ha garantizado. | AD32: =IF(AND(COUNTIF($B$5:B32,B32)=1,$B32<>"",$AB32<>""),1,0) | AE32: https://www.eltiempo.com/opinion/columnistas/una-batalla-sin-partidos-3556318
A33: ART_013 | B33: ART_013_S06 | C33: El Tiempo | D33: Política | E33: Opinión-análisis | F33: 2026-05-16T23:45:00-05:00 | G33: A ello se suma el apoyo de las bandas armadas que saben que con Cepeda seguirían gozando de la escandalosa impunidad que Petro les ha garantizado. | H33: La chequera del régimen petrista ha regado cientos de municipios con miles y miles de millones de pesos en contratos de obras y servicios, así como en órdenes de trabajo individuales. | AD33: =IF(AND(COUNTIF($B$5:B33,B33)=1,$B33<>"",$AB33<>""),1,0) | AE33: https://www.eltiempo.com/opinion/columnistas/una-batalla-sin-partidos-3556318
A34: ART_014 | B34: ART_014_S01 | C34: El Espectador | D34: Política | E34: Noticia dura | F34: Fri, 04 Sep 2026 23:58:00 +0000 | G34: La aerolínea Avianca confirmó que canceló los tiquetes adquiridos por el expresidente Gustavo Petro para su viaje a México debido a que está incluido en la lista OFAC. | I34: El expresidente les respondió. | AD34: =IF(AND(COUNTIF($B$5:B34,B34)=1,$B34<>"",$AB34<>""),1,0) | AE34: https://www.elespectador.com/politica/avianca-confirma-que-cancelo-tiquetes-de-petro-a-mexico-esto-dijo-el-expresidente/
A35: ART_014 | B35: ART_014_S02 | C35: El Espectador | D35: Política | E35: Noticia dura | F35: Fri, 04 Sep 2026 23:58:00 +0000 | G35: El expresidente les respondió. | H35: La aerolínea Avianca confirmó que canceló los tiquetes adquiridos por el expresidente Gustavo Petro para su viaje a México debido a que está incluido en la lista OFAC. | I35: Avianca aseguró que al ser una aerolínea colombiana que opera en territorio estadounidense y “realiza de forma permanente transacciones con su sistema financiero”, se encuentra sujeta a “las regulaciones de sanciones económicas administradas por la Oficina de Control de Activos Extranjeros (OFAC por sus siglas en inglés) del Departamento del Tesoro de los Estados Unidos de América”. | AD35: =IF(AND(COUNTIF($B$5:B35,B35)=1,$B35<>"",$AB35<>""),1,0) | AE35: https://www.elespectador.com/politica/avianca-confirma-que-cancelo-tiquetes-de-petro-a-mexico-esto-dijo-el-expresidente/
A36: ART_014 | B36: ART_014_S03 | C36: El Espectador | D36: Política | E36: Noticia dura | F36: Fri, 04 Sep 2026 23:58:00 +0000 | G36: Avianca aseguró que al ser una aerolínea colombiana que opera en territorio estadounidense y “realiza de forma permanente transacciones con su sistema financiero”, se encuentra sujeta a “las regulaciones de sanciones económicas administradas por la Oficina de Control de Activos Extranjeros (OFAC por sus siglas en inglés) del Departamento del Tesoro de los Estados Unidos de América”. | H36: El expresidente les respondió. | I36: “Dichas regulaciones prohíben a las personas y entidades que, como Avianca, tienen vínculos económicos y financieros con los Estados Unidos de América, realizar transacciones, incluida la prestación de servicios, a favor de cualquier persona cuyos bienes e intereses se encuentren bloqueados por figurar en la Lista de Nacionales Especialmente Designados y Personas Bloqueadas (Lista SDN)”, agregaron. | AD36: =IF(AND(COUNTIF($B$5:B36,B36)=1,$B36<>"",$AB36<>""),1,0) | AE36: https://www.elespectador.com/politica/avianca-confirma-que-cancelo-tiquetes-de-petro-a-mexico-esto-dijo-el-expresidente/
A37: ART_014 | B37: ART_014_S04 | C37: El Espectador | D37: Política | E37: Noticia dura | F37: Fri, 04 Sep 2026 23:58:00 +0000 | G37: “Dichas regulaciones prohíben a las personas y entidades que, como Avianca, tienen vínculos económicos y financieros con los Estados Unidos de América, realizar transacciones, incluida la prestación de servicios, a favor de cualquier persona cuyos bienes e intereses se encuentren bloqueados por figurar en la Lista de Nacionales Especialmente Designados y Personas Bloqueadas (Lista SDN)”, agregaron. | H37: Avianca aseguró que al ser una aerolínea colombiana que opera en territorio estadounidense y “realiza de forma permanente transacciones con su sistema financiero”, se encuentra sujeta a “las regulaciones de sanciones económicas administradas por la Oficina de Control de Activos Extranjeros (OFAC por sus siglas en inglés) del Departamento del Tesoro de los Estados Unidos de América”. | I37: Por esta razón, la aerolínea canceló las reservas que fueron hechas por el expresidente Gustavo Petro y reembolsó la totalidad del valor que había sido pagado. | AD37: =IF(AND(COUNTIF($B$5:B37,B37)=1,$B37<>"",$AB37<>""),1,0) | AE37: https://www.elespectador.com/politica/avianca-confirma-que-cancelo-tiquetes-de-petro-a-mexico-esto-dijo-el-expresidente/
A38: ART_014 | B38: ART_014_S05 | C38: El Espectador | D38: Política | E38: Noticia dura | F38: Fri, 04 Sep 2026 23:58:00 +0000 | G38: Por esta razón, la aerolínea canceló las reservas que fueron hechas por el expresidente Gustavo Petro y reembolsó la totalidad del valor que había sido pagado. | H38: “Dichas regulaciones prohíben a las personas y entidades que, como Avianca, tienen vínculos económicos y financieros con los Estados Unidos de América, realizar transacciones, incluida la prestación de servicios, a favor de cualquier persona cuyos bienes e intereses se encuentren bloqueados por figurar en la Lista de Nacionales Especialmente Designados y Personas Bloqueadas (Lista SDN)”, agregaron. | AD38: =IF(AND(COUNTIF($B$5:B38,B38)=1,$B38<>"",$AB38<>""),1,0) | AE38: https://www.elespectador.com/politica/avianca-confirma-que-cancelo-tiquetes-de-petro-a-mexico-esto-dijo-el-expresidente/
A39: ART_015 | B39: ART_015_S01 | C39: El Espectador | D39: Política | E39: Noticia dura | F39: Sun, 06 Sep 2026 00:22:17 +0000 | G39: El general (r) Jorge Eduardo Mora, junto con la cúpula militar y de Policía, anunció un nuevo paquete de medidas para reforzar la seguridad y el control territorial en Ocaña y el Catatumbo, tras el ataque terrorista perpetrado por el Eln la noche del pasado 4 de septiembre contra el Cantón Militar El Trapiche, que dejó tres militares muertos. | I39: Las decisiones se adoptaron en un consejo de seguridad en el que participaron el gobernador de Norte de Santander y altos mandos militares y policiales de la región. | AD39: =IF(AND(COUNTIF($B$5:B39,B39)=1,$B39<>"",$AB39<>""),1,0) | AE39: https://www.elespectador.com/judicial/mindefensa-anuncia-nuevas-medidas-de-seguridad-tras-ataque-con-drones-del-eln-en-ocana/
A40: ART_015 | B40: ART_015_S02 | C40: El Espectador | D40: Política | E40: Noticia dura | F40: Sun, 06 Sep 2026 00:22:17 +0000 | G40: Las decisiones se adoptaron en un consejo de seguridad en el que participaron el gobernador de Norte de Santander y altos mandos militares y policiales de la región. | H40: El general (r) Jorge Eduardo Mora, junto con la cúpula militar y de Policía, anunció un nuevo paquete de medidas para reforzar la seguridad y el control territorial en Ocaña y el Catatumbo, tras el ataque terrorista perpetrado por el Eln la noche del pasado 4 de septiembre contra el Cantón Militar El Trapiche, que dejó tres militares muertos. | I40: Como primera medida, se ordenó la reestructuración, reorganización y activación de la campaña militar y policial “Esparta”, que tendrá su sede en Ocaña y buscará articular las capacidades de las Fuerzas Militares y de la Policía Nacional para enfrentar a las estructuras criminales que operan en la zona. | AD40: =IF(AND(COUNTIF($B$5:B40,B40)=1,$B40<>"",$AB40<>""),1,0) | AE40: https://www.elespectador.com/judicial/mindefensa-anuncia-nuevas-medidas-de-seguridad-tras-ataque-con-drones-del-eln-en-ocana/
A41: ART_015 | B41: ART_015_S03 | C41: El Espectador | D41: Política | E41: Noticia dura | F41: Sun, 06 Sep 2026 00:22:17 +0000 | G41: Como primera medida, se ordenó la reestructuración, reorganización y activación de la campaña militar y policial “Esparta”, que tendrá su sede en Ocaña y buscará articular las capacidades de las Fuerzas Militares y de la Policía Nacional para enfrentar a las estructuras criminales que operan en la zona. | H41: Las decisiones se adoptaron en un consejo de seguridad en el que participaron el gobernador de Norte de Santander y altos mandos militares y policiales de la región. | I41: También se dispuso fortalecer el bloqueo y la contención de los corredores utilizados por los grupos armados ilegales para movilizar hombres, armas, explosivos y recursos ilícitos entre el sur del Cesar y Ocaña. | AD41: =IF(AND(COUNTIF($B$5:B41,B41)=1,$B41<>"",$AB41<>""),1,0) | AE41: https://www.elespectador.com/judicial/mindefensa-anuncia-nuevas-medidas-de-seguridad-tras-ataque-con-drones-del-eln-en-ocana/
A42: ART_015 | B42: ART_015_S04 | C42: El Espectador | D42: Política | E42: Noticia dura | F42: Sun, 06 Sep 2026 00:22:17 +0000 | G42: También se dispuso fortalecer el bloqueo y la contención de los corredores utilizados por los grupos armados ilegales para movilizar hombres, armas, explosivos y recursos ilícitos entre el sur del Cesar y Ocaña. | H42: Como primera medida, se ordenó la reestructuración, reorganización y activación de la campaña militar y policial “Esparta”, que tendrá su sede en Ocaña y buscará articular las capacidades de las Fuerzas Militares y de la Policía Nacional para enfrentar a las estructuras criminales que operan en la zona. | AD42: =IF(AND(COUNTIF($B$5:B42,B42)=1,$B42<>"",$AB42<>""),1,0) | AE42: https://www.elespectador.com/judicial/mindefensa-anuncia-nuevas-medidas-de-seguridad-tras-ataque-con-drones-del-eln-en-ocana/
A43: ART_016 | B43: ART_016_S01 | C43: El Espectador | D43: Política | E43: Noticia dura | F43: 2026-05-12T19:11:23-05:00 | G43: Las pensiones son, por lo general, un tema que, aunque vital, no suele generar muchos titulares en la vida nacional. | I43: Suceden en un rimo casi que automático: manejan billones de pesos que involucran el bienestar de millones de personas, pero nadie parece reparar mucho en ellas. | AD43: =IF(AND(COUNTIF($B$5:B43,B43)=1,$B43<>"",$AB43<>""),1,0) | AE43: https://www.elespectador.com/economia/macroeconomia/pensiones-en-colombia-2026-la-historia-del-enredo-entre-la-reforma-la-corte-constitucional-y-los-fondos-privados/
A44: ART_016 | B44: ART_016_S02 | C44: El Espectador | D44: Política | E44: Noticia dura | F44: 2026-05-12T19:11:23-05:00 | G44: Suceden en un rimo casi que automático: manejan billones de pesos que involucran el bienestar de millones de personas, pero nadie parece reparar mucho en ellas. | H44: Las pensiones son, por lo general, un tema que, aunque vital, no suele generar muchos titulares en la vida nacional. | I44: Pero desde hace unas semanas, la palabra pensiones hace que más de un funcionario público salte de su asiento, con una mezcla entre alarma, indignación y hasta algo de pelea de colegio, a juzgar por las recientes reacciones del Gobierno frente a dos medidas del Consejo de Estado, que suspendieron los efectos de un decreto que buscaba que los fondos privados le transfirieran unos COP 25 billones en ahorro pensional a Colpensiones. | AD44: =IF(AND(COUNTIF($B$5:B44,B44)=1,$B44<>"",$AB44<>""),1,0) | AE44: https://www.elespectador.com/economia/macroeconomia/pensiones-en-colombia-2026-la-historia-del-enredo-entre-la-reforma-la-corte-constitucional-y-los-fondos-privados/
A45: ART_016 | B45: ART_016_S03 | C45: El Espectador | D45: Política | E45: Noticia dura | F45: 2026-05-12T19:11:23-05:00 | G45: Pero desde hace unas semanas, la palabra pensiones hace que más de un funcionario público salte de su asiento, con una mezcla entre alarma, indignación y hasta algo de pelea de colegio, a juzgar por las recientes reacciones del Gobierno frente a dos medidas del Consejo de Estado, que suspendieron los efectos de un decreto que buscaba que los fondos privados le transfirieran unos COP 25 billones en ahorro pensional a Colpensiones. | H45: Suceden en un rimo casi que automático: manejan billones de pesos que involucran el bienestar de millones de personas, pero nadie parece reparar mucho en ellas. | I45: Esto, en voz de expertos y analistas, en directa contravía con lo dispuestos en uno de los dos artículos de la reforma pensional que siguen activos mientras el resto de la iniciativa sigue bajo la lupa de la Corte Constitucional. | AD45: =IF(AND(COUNTIF($B$5:B45,B45)=1,$B45<>"",$AB45<>""),1,0) | AE45: https://www.elespectador.com/economia/macroeconomia/pensiones-en-colombia-2026-la-historia-del-enredo-entre-la-reforma-la-corte-constitucional-y-los-fondos-privados/
A46: ART_016 | B46: ART_016_S04 | C46: El Espectador | D46: Política | E46: Noticia dura | F46: 2026-05-12T19:11:23-05:00 | G46: Esto, en voz de expertos y analistas, en directa contravía con lo dispuestos en uno de los dos artículos de la reforma pensional que siguen activos mientras el resto de la iniciativa sigue bajo la lupa de la Corte Constitucional. | H46: Pero desde hace unas semanas, la palabra pensiones hace que más de un funcionario público salte de su asiento, con una mezcla entre alarma, indignación y hasta algo de pelea de colegio, a juzgar por las recientes reacciones del Gobierno frente a dos medidas del Consejo de Estado, que suspendieron los efectos de un decreto que buscaba que los fondos privados le transfirieran unos COP 25 billones en ahorro pensional a Colpensiones. | I46: Para este punto de la historia, la discusión puede marear un poco, entre el cruce de declaraciones que este martes ya incluía a la Corte Suprema y a varios ministerios, además del presidente Petro, siempre activo con las descalificaciones a través de su cuenta de X. | AD46: =IF(AND(COUNTIF($B$5:B46,B46)=1,$B46<>"",$AB46<>""),1,0) | AE46: https://www.elespectador.com/economia/macroeconomia/pensiones-en-colombia-2026-la-historia-del-enredo-entre-la-reforma-la-corte-constitucional-y-los-fondos-privados/
A47: ART_016 | B47: ART_016_S05 | C47: El Espectador | D47: Política | E47: Noticia dura | F47: 2026-05-12T19:11:23-05:00 | G47: Para este punto de la historia, la discusión puede marear un poco, entre el cruce de declaraciones que este martes ya incluía a la Corte Suprema y a varios ministerios, además del presidente Petro, siempre activo con las descalificaciones a través de su cuenta de X. | H47: Esto, en voz de expertos y analistas, en directa contravía con lo dispuestos en uno de los dos artículos de la reforma pensional que siguen activos mientras el resto de la iniciativa sigue bajo la lupa de la Corte Constitucional. | I47: Entonces, ¿por qué es que no tenemos claras las reglas sobre pensiones para este punto? | AD47: =IF(AND(COUNTIF($B$5:B47,B47)=1,$B47<>"",$AB47<>""),1,0) | AE47: https://www.elespectador.com/economia/macroeconomia/pensiones-en-colombia-2026-la-historia-del-enredo-entre-la-reforma-la-corte-constitucional-y-los-fondos-privados/
A48: ART_016 | B48: ART_016_S06 | C48: El Espectador | D48: Política | E48: Noticia dura | F48: 2026-05-12T19:11:23-05:00 | G48: Entonces, ¿por qué es que no tenemos claras las reglas sobre pensiones para este punto? | H48: Para este punto de la historia, la discusión puede marear un poco, entre el cruce de declaraciones que este martes ya incluía a la Corte Suprema y a varios ministerios, además del presidente Petro, siempre activo con las descalificaciones a través de su cuenta de X. | AD48: =IF(AND(COUNTIF($B$5:B48,B48)=1,$B48<>"",$AB48<>""),1,0) | AE48: https://www.elespectador.com/economia/macroeconomia/pensiones-en-colombia-2026-la-historia-del-enredo-entre-la-reforma-la-corte-constitucional-y-los-fondos-privados/
A49: ART_017 | B49: ART_017_S01 | C49: El Espectador | D49: Política | E49: Noticia dura | F49: 2026-09-02T20:27:20-05:00 | G49: Tras la conmoción que generó el atentado con explosivos contra la estación de Policía de Los Patios, en Norte de Santander, el gobierno anunció que intensificará la ofensiva contra los grupos armados y organizaciones criminales detrás de estos casos. | I49: De acuerdo con el jefe de la cartera política, el ministro Rodrigo Lara, el eje de esta estrategia será un estatuto antiterrorista que será puesto a discusión en el Congreso. | AD49: =IF(AND(COUNTIF($B$5:B49,B49)=1,$B49<>"",$AB49<>""),1,0) | AE49: https://www.elespectador.com/politica/gobierno-de-la-espriella-prepara-un-estatuto-antiterrorista-que-sera-radicado-ante-el-congreso-esto-se-sabe/
A50: ART_017 | B50: ART_017_S02 | C50: El Espectador | D50: Política | E50: Noticia dura | F50: 2026-09-02T20:27:20-05:00 | G50: De acuerdo con el jefe de la cartera política, el ministro Rodrigo Lara, el eje de esta estrategia será un estatuto antiterrorista que será puesto a discusión en el Congreso. | H50: Tras la conmoción que generó el atentado con explosivos contra la estación de Policía de Los Patios, en Norte de Santander, el gobierno anunció que intensificará la ofensiva contra los grupos armados y organizaciones criminales detrás de estos casos. | I50: La apuesta obedece directamente a lo que le ha pedido el presidente Abelardo de la Espriella a las fuerzas militares: una ofensiva frontal contra estos grupos. | AD50: =IF(AND(COUNTIF($B$5:B50,B50)=1,$B50<>"",$AB50<>""),1,0) | AE50: https://www.elespectador.com/politica/gobierno-de-la-espriella-prepara-un-estatuto-antiterrorista-que-sera-radicado-ante-el-congreso-esto-se-sabe/
A51: ART_017 | B51: ART_017_S03 | C51: El Espectador | D51: Política | E51: Noticia dura | F51: 2026-09-02T20:27:20-05:00 | G51: La apuesta obedece directamente a lo que le ha pedido el presidente Abelardo de la Espriella a las fuerzas militares: una ofensiva frontal contra estos grupos. | H51: De acuerdo con el jefe de la cartera política, el ministro Rodrigo Lara, el eje de esta estrategia será un estatuto antiterrorista que será puesto a discusión en el Congreso. | I51: El jefe de Estado ha dicho en varias oportunidades que declarará a dichas estructuras como terroristas, lo que también implica cerrarles la puerta a los diálogos de paz. | AD51: =IF(AND(COUNTIF($B$5:B51,B51)=1,$B51<>"",$AB51<>""),1,0) | AE51: https://www.elespectador.com/politica/gobierno-de-la-espriella-prepara-un-estatuto-antiterrorista-que-sera-radicado-ante-el-congreso-esto-se-sabe/
A52: ART_017 | B52: ART_017_S04 | C52: El Espectador | D52: Política | E52: Noticia dura | F52: 2026-09-02T20:27:20-05:00 | G52: El jefe de Estado ha dicho en varias oportunidades que declarará a dichas estructuras como terroristas, lo que también implica cerrarles la puerta a los diálogos de paz. | H52: La apuesta obedece directamente a lo que le ha pedido el presidente Abelardo de la Espriella a las fuerzas militares: una ofensiva frontal contra estos grupos. | I52: El ministro Lara aseguró que el estatuto antiterrorista contempla, precisamente, crear esa lista de esos grupos terroristas y darle luz verde a unas herramientas más potentes en materia jurídica para combatirlos. | AD52: =IF(AND(COUNTIF($B$5:B52,B52)=1,$B52<>"",$AB52<>""),1,0) | AE52: https://www.elespectador.com/politica/gobierno-de-la-espriella-prepara-un-estatuto-antiterrorista-que-sera-radicado-ante-el-congreso-esto-se-sabe/
A53: ART_017 | B53: ART_017_S05 | C53: El Espectador | D53: Política | E53: Noticia dura | F53: 2026-09-02T20:27:20-05:00 | G53: El ministro Lara aseguró que el estatuto antiterrorista contempla, precisamente, crear esa lista de esos grupos terroristas y darle luz verde a unas herramientas más potentes en materia jurídica para combatirlos. | H53: El jefe de Estado ha dicho en varias oportunidades que declarará a dichas estructuras como terroristas, lo que también implica cerrarles la puerta a los diálogos de paz. | AD53: =IF(AND(COUNTIF($B$5:B53,B53)=1,$B53<>"",$AB53<>""),1,0) | AE53: https://www.elespectador.com/politica/gobierno-de-la-espriella-prepara-un-estatuto-antiterrorista-que-sera-radicado-ante-el-congreso-esto-se-sabe/
A54: ART_018 | B54: ART_018_S01 | C54: La Silla Vacía | D54: Política | E54: Noticia dura | F54: Wed, 26 Aug 2026 00:50:09 +0000 | G54: Con una votación de 7 a 1, la Corte Constitucional avaló la mayoría del articulado de la reforma pensional del gobierno de Gustavo Petro, pero le pidió a la Cámara discutir —en un plazo de 30 días— nueve proposiciones puntuales y un artículo nuevo. | AD54: =IF(AND(COUNTIF($B$5:B54,B54)=1,$B54<>"",$AB54<>""),1,0) | AE54: https://www.lasillavacia.com/en-vivo/reforma-pensional-corte-avala-90-articulos-y-devuelve-9-a-la-camara/
A55: ART_019 | B55: ART_019_S01 | C55: La Silla Vacía | D55: Política | E55: Noticia dura | F55: Fri, 26 Dec 2025 05:05:00 +0000 | G55: A la impredictibilidad del presidente Gustavo Petro se sumó el inmenso cambio en el equilibrio de poder mundial producido por la llegada de Donald Trump a la Casa Blanca. | AD55: =IF(AND(COUNTIF($B$5:B55,B55)=1,$B55<>"",$AB55<>""),1,0) | AE55: https://www.lasillavacia.com/silla-nacional/asi-se-transformo-el-poder-en-colombia-en-2025/
A56: ART_020 | B56: ART_020_S01 | C56: La Silla Vacía | D56: Política | E56: Opinión-análisis | F56: Fri, 04 Sep 2026 19:00:00 +0000 | G56: Esta disminución sí es de este gobierno y ninguna corrección aritmética lo borra. | AD56: =IF(AND(COUNTIF($B$5:B56,B56)=1,$B56<>"",$AB56<>""),1,0) | AE56: https://www.lasillavacia.com/red-de-expertos/red-social/el-presupuesto-de-cultura-bajo-pero-no-por-la-cifra-que-dicen/
A57: ART_021 | B57: ART_021_S01 | C57: La Silla Vacía | D57: Política | E57: Opinión-análisis | F57: Thu, 03 Sep 2026 21:00:00 +0000 | G57: Una política de seguridad no debería preguntarse únicamente cuántos fueron capturados o abatidos hoy, sino cuánta capacidad criminal dejó de existir. | AD57: =IF(AND(COUNTIF($B$5:B57,B57)=1,$B57<>"",$AB57<>""),1,0) | AE57: https://www.lasillavacia.com/red-de-expertos/red-de-la-paz/contar-capturas-y-bajas-no-mide-la-seguridad-en-colombia/
A58: ART_022 | B58: ART_022_S01 | C58: La Silla Vacía | D58: Política | E58: Opinión-análisis | F58: Sat, 05 Sep 2026 19:00:00 +0000 | G58: Durante la última semana causó revuelo la noticia divulgada por Caracol Radio, señalando la existencia de presuntas actas que develaban que el presidente De la Espriella habría ordenado a sus ministros no conceder ruedas de prensa ni entrevistas a medios de comunicación que no fueran ‘amigos’, salvo para temas estratégicos o con previa autorización. | AD58: =IF(AND(COUNTIF($B$5:B58,B58)=1,$B58<>"",$AB58<>""),1,0) | AE58: https://www.lasillavacia.com/red-de-expertos/red-social/la-informacion-publica-no-se-restringe-a-medios-amigos/
A59: ART_023 | B59: ART_023_S01 | C59: La Silla Vacía | D59: Política | E59: Opinión-análisis | F59: Sat, 05 Sep 2026 16:33:03 +0000 | G59: ¿Operaciones sin Seguridad? Me preguntaba un amigo, que opinaba sobre las anunciadas operaciones militares en Chiribiquete. | AD59: =IF(AND(COUNTIF($B$5:B59,B59)=1,$B59<>"",$AB59<>""),1,0) | AE59: https://www.lasillavacia.com/opinion/operaciones-sin-seguridad/
A60: ART_024 | B60: ART_024_S01 | C60: La Silla Vacía | D60: Política | E60: Opinión-análisis | F60: Mon, 31 Aug 2026 18:10:17 +0000 | G60: Tras mantener suspendida su entrada en vigor cerca de dos años, la Corte Constitucional declaró exequible el grueso de la Ley 2381 de 2024 y difirió su vigencia al 1.º de abril de 2027. | AD60: =IF(AND(COUNTIF($B$5:B60,B60)=1,$B60<>"",$AB60<>""),1,0) | AE60: https://www.lasillavacia.com/red-de-expertos/red-de-derecho-constitucional/ganadores-y-perdedores-de-la-reforma-pensional/
A61: ART_025 | B61: ART_025_S01 | C61: La Silla Vacía | D61: Política | E61: Opinión-análisis | F61: 2025-04-05T05:05:00+00:00 | G61: Se ha dicho que los aranceles del 10 % impuestos por Trump a Colombia tienen algunos efectos positivos y que el país salió relativamente bien librado. | AD61: =IF(AND(COUNTIF($B$5:B61,B61)=1,$B61<>"",$AB61<>""),1,0) | AE61: https://www.lasillavacia.com/red-de-expertos/red-social/colombia-no-sale-tan-bien-librada-con-los-nuevos-aranceles-de-trump/
A62: ART_026 | B62: ART_026_S01 | C62: La Silla Vacía | D62: Política | E62: Opinión-análisis | F62: Thu, 27 Aug 2026 13:00:00 +0000 | G62: La reforma pensional colombiana dejó de ser solamente una discusión sobre el futuro de los trabajadores y se convirtió también en un asunto de economía de empresa. | AD62: =IF(AND(COUNTIF($B$5:B62,B62)=1,$B62<>"",$AB62<>""),1,0) | AE62: https://www.lasillavacia.com/red-de-expertos/red-social/pension-un-reto-economico-y-empresarial/
A63: ART_027 | B63: ART_027_S01 | C63: La Silla Vacía | D63: Política | E63: Opinión-análisis | F63: Tue, 23 Jun 2026 20:03:13 +0000 | G63: El politólogo Guillermo O’Donnell advirtió que la democracia no se agota en las elecciones porque exige también que el Estado garantice el imperio de la ley en todo el territorio y que los ciudadanos puedan ejercer sus derechos sin coacción. | AD63: =IF(AND(COUNTIF($B$5:B63,B63)=1,$B63<>"",$AB63<>""),1,0) | AE63: https://www.lasillavacia.com/red-de-expertos/red-de-la-paz/elecciones-y-crimen-organizado-una-reflexion-academica/
A64: ART_028 | B64: ART_028_S01 | C64: La Silla Vacía | D64: Política | E64: Opinión-análisis | F64: 2025-03-24T15:29:59+00:00 | G64: La guerra comercial que ha desatado el presidente Trump en varias zonas del planeta tiene a todos los países en alerta, debido a los posibles efectos negativos que esta puede generar en sus economías. | AD64: =IF(AND(COUNTIF($B$5:B64,B64)=1,$B64<>"",$AB64<>""),1,0) | AE64: https://www.lasillavacia.com/red-de-expertos/red-social/guerra-comercial-de-trump-oportunidad-para-colombia/
A65: ART_029 | B65: ART_029_S01 | C65: Semana | D65: Política | E65: Noticia dura | F65: Fri, 04 Sep 2026 20:38:57 +0000 | G65: Por medio de su cuenta de Instagram, el presidente Abelardo De La Espriella publicó una historia que no pasó desapercibida y que llamó la atención de los usuarios de las redes sociales. | I65: Se trata de una foto en la que se ve al mandatario junto a integrantes de la Fuerza Pública, la cual está acompañada de un mensaje que vaticinaba la suerte que iba a tener el cabecilla Naín Andrés Pérez, más conocido con el alias de Bendito Menor. | AD65: =IF(AND(COUNTIF($B$5:B65,B65)=1,$B65<>"",$AB65<>""),1,0) | AE65: https://www.semana.com/politica/articulo/la-publicacion-de-abelardo-de-la-espriella-que-vaticinaba-la-suerte-que-iba-a-tener-alias-bendito-menor-que-impacto-las-redes/202657/
A66: ART_029 | B66: ART_029_S02 | C66: Semana | D66: Política | E66: Noticia dura | F66: Fri, 04 Sep 2026 20:38:57 +0000 | G66: Se trata de una foto en la que se ve al mandatario junto a integrantes de la Fuerza Pública, la cual está acompañada de un mensaje que vaticinaba la suerte que iba a tener el cabecilla Naín Andrés Pérez, más conocido con el alias de Bendito Menor. | H66: Por medio de su cuenta de Instagram, el presidente Abelardo De La Espriella publicó una historia que no pasó desapercibida y que llamó la atención de los usuarios de las redes sociales. | I66: “Quien decida continuar atacando a Colombia, encontrará enfrente toda la capacidad legítima del Estado”, expresó la publicación en la cuenta de Instagram del mandatario. | AD66: =IF(AND(COUNTIF($B$5:B66,B66)=1,$B66<>"",$AB66<>""),1,0) | AE66: https://www.semana.com/politica/articulo/la-publicacion-de-abelardo-de-la-espriella-que-vaticinaba-la-suerte-que-iba-a-tener-alias-bendito-menor-que-impacto-las-redes/202657/
A67: ART_029 | B67: ART_029_S03 | C67: Semana | D67: Política | E67: Noticia dura | F67: Fri, 04 Sep 2026 20:38:57 +0000 | G67: “Quien decida continuar atacando a Colombia, encontrará enfrente toda la capacidad legítima del Estado”, expresó la publicación en la cuenta de Instagram del mandatario. | H67: Se trata de una foto en la que se ve al mandatario junto a integrantes de la Fuerza Pública, la cual está acompañada de un mensaje que vaticinaba la suerte que iba a tener el cabecilla Naín Andrés Pérez, más conocido con el alias de Bendito Menor. | I67: Frente al caso de alias Bendito Menor, ese peligroso cabecilla fue dado de baja por una acción articulada que desplegó la Policía Nacional en el departamento de La Guajira. | AD67: =IF(AND(COUNTIF($B$5:B67,B67)=1,$B67<>"",$AB67<>""),1,0) | AE67: https://www.semana.com/politica/articulo/la-publicacion-de-abelardo-de-la-espriella-que-vaticinaba-la-suerte-que-iba-a-tener-alias-bendito-menor-que-impacto-las-redes/202657/
A68: ART_029 | B68: ART_029_S04 | C68: Semana | D68: Política | E68: Noticia dura | F68: Fri, 04 Sep 2026 20:38:57 +0000 | G68: Frente al caso de alias Bendito Menor, ese peligroso cabecilla fue dado de baja por una acción articulada que desplegó la Policía Nacional en el departamento de La Guajira. | H68: “Quien decida continuar atacando a Colombia, encontrará enfrente toda la capacidad legítima del Estado”, expresó la publicación en la cuenta de Instagram del mandatario. | I68: El presidente De La Espriella, este viernes, 4 de septiembre, reveló detalles de la operación: “Hoy es un gran día para Colombia. | AD68: =IF(AND(COUNTIF($B$5:B68,B68)=1,$B68<>"",$AB68<>""),1,0) | AE68: https://www.semana.com/politica/articulo/la-publicacion-de-abelardo-de-la-espriella-que-vaticinaba-la-suerte-que-iba-a-tener-alias-bendito-menor-que-impacto-las-redes/202657/
A69: ART_029 | B69: ART_029_S05 | C69: Semana | D69: Política | E69: Noticia dura | F69: Fri, 04 Sep 2026 20:38:57 +0000 | G69: El presidente De La Espriella, este viernes, 4 de septiembre, reveló detalles de la operación: “Hoy es un gran día para Colombia. | H69: Frente al caso de alias Bendito Menor, ese peligroso cabecilla fue dado de baja por una acción articulada que desplegó la Policía Nacional en el departamento de La Guajira. | I69: Gracias a una operación impecable realizada por nuestra Policía Nacional por un comando especial de la Dijín, se dio de baja a uno de los más peligrosos delincuentes de nuestro país, alias Naín o Bendito Menor”. | AD69: =IF(AND(COUNTIF($B$5:B69,B69)=1,$B69<>"",$AB69<>""),1,0) | AE69: https://www.semana.com/politica/articulo/la-publicacion-de-abelardo-de-la-espriella-que-vaticinaba-la-suerte-que-iba-a-tener-alias-bendito-menor-que-impacto-las-redes/202657/
A70: ART_029 | B70: ART_029_S06 | C70: Semana | D70: Política | E70: Noticia dura | F70: Fri, 04 Sep 2026 20:38:57 +0000 | G70: Gracias a una operación impecable realizada por nuestra Policía Nacional por un comando especial de la Dijín, se dio de baja a uno de los más peligrosos delincuentes de nuestro país, alias Naín o Bendito Menor”. | H70: El presidente De La Espriella, este viernes, 4 de septiembre, reveló detalles de la operación: “Hoy es un gran día para Colombia. | I70: “Hoy ha llegado el fin de las actividades criminales de este narcoterrorista que tenía azotada a La Guajira y al Caribe colombiano mediante el narcotráfico, la extorsión y la presión a la población. | AD70: =IF(AND(COUNTIF($B$5:B70,B70)=1,$B70<>"",$AB70<>""),1,0) | AE70: https://www.semana.com/politica/articulo/la-publicacion-de-abelardo-de-la-espriella-que-vaticinaba-la-suerte-que-iba-a-tener-alias-bendito-menor-que-impacto-las-redes/202657/
A71: ART_029 | B71: ART_029_S07 | C71: Semana | D71: Política | E71: Noticia dura | F71: Fri, 04 Sep 2026 20:38:57 +0000 | G71: “Hoy ha llegado el fin de las actividades criminales de este narcoterrorista que tenía azotada a La Guajira y al Caribe colombiano mediante el narcotráfico, la extorsión y la presión a la población. | H71: Gracias a una operación impecable realizada por nuestra Policía Nacional por un comando especial de la Dijín, se dio de baja a uno de los más peligrosos delincuentes de nuestro país, alias Naín o Bendito Menor”. | I71: Este delincuente, que no seguirá delinquiendo porque le cayó la mano de hierro del Estado, tenía arrodillada a la población, llena de miedo”, afirmó el mandatario colombiano en una declaración que dio desde La Guajira. | AD71: =IF(AND(COUNTIF($B$5:B71,B71)=1,$B71<>"",$AB71<>""),1,0) | AE71: https://www.semana.com/politica/articulo/la-publicacion-de-abelardo-de-la-espriella-que-vaticinaba-la-suerte-que-iba-a-tener-alias-bendito-menor-que-impacto-las-redes/202657/
A72: ART_029 | B72: ART_029_S08 | C72: Semana | D72: Política | E72: Noticia dura | F72: Fri, 04 Sep 2026 20:38:57 +0000 | G72: Este delincuente, que no seguirá delinquiendo porque le cayó la mano de hierro del Estado, tenía arrodillada a la población, llena de miedo”, afirmó el mandatario colombiano en una declaración que dio desde La Guajira. | H72: “Hoy ha llegado el fin de las actividades criminales de este narcoterrorista que tenía azotada a La Guajira y al Caribe colombiano mediante el narcotráfico, la extorsión y la presión a la población. | I72: También expresó: “En el Gobierno del Tigre la gente de bien no volverá a sentir miedo. | AD72: =IF(AND(COUNTIF($B$5:B72,B72)=1,$B72<>"",$AB72<>""),1,0) | AE72: https://www.semana.com/politica/articulo/la-publicacion-de-abelardo-de-la-espriella-que-vaticinaba-la-suerte-que-iba-a-tener-alias-bendito-menor-que-impacto-las-redes/202657/
A73: ART_029 | B73: ART_029_S09 | C73: Semana | D73: Política | E73: Noticia dura | F73: Fri, 04 Sep 2026 20:38:57 +0000 | G73: También expresó: “En el Gobierno del Tigre la gente de bien no volverá a sentir miedo. | H73: Este delincuente, que no seguirá delinquiendo porque le cayó la mano de hierro del Estado, tenía arrodillada a la población, llena de miedo”, afirmó el mandatario colombiano en una declaración que dio desde La Guajira. | I73: Los que tienen que sentir pánico y terror son los delincuentes, porque aquellos que no se sometan terminarán de esta forma. | AD73: =IF(AND(COUNTIF($B$5:B73,B73)=1,$B73<>"",$AB73<>""),1,0) | AE73: https://www.semana.com/politica/articulo/la-publicacion-de-abelardo-de-la-espriella-que-vaticinaba-la-suerte-que-iba-a-tener-alias-bendito-menor-que-impacto-las-redes/202657/
A74: ART_029 | B74: ART_029_S10 | C74: Semana | D74: Política | E74: Noticia dura | F74: Fri, 04 Sep 2026 20:38:57 +0000 | G74: Los que tienen que sentir pánico y terror son los delincuentes, porque aquellos que no se sometan terminarán de esta forma. | H74: También expresó: “En el Gobierno del Tigre la gente de bien no volverá a sentir miedo. | AD74: =IF(AND(COUNTIF($B$5:B74,B74)=1,$B74<>"",$AB74<>""),1,0) | AE74: https://www.semana.com/politica/articulo/la-publicacion-de-abelardo-de-la-espriella-que-vaticinaba-la-suerte-que-iba-a-tener-alias-bendito-menor-que-impacto-las-redes/202657/
A75: ART_030 | B75: ART_030_S01 | C75: Semana | D75: Política | E75: Noticia dura | F75: Thu, 03 Sep 2026 02:25:55 +0000 | G75: La Corte Constitucional señaló que el auxilio funerario contemplado dentro del sistema pensional se mantendrá en Colombia a partir de 2027, despejando así una de las dudas que había surgido alrededor de la entrada en vigencia de la reforma pensional. | I75: Según Valora Analitik, la decisión se conoció luego de que el alto tribunal revisara las disposiciones de la reforma que cambiarán las reglas del sistema de pensiones. | AD75: =IF(AND(COUNTIF($B$5:B75,B75)=1,$B75<>"",$AB75<>""),1,0) | AE75: https://www.semana.com/economia/management/articulo/se-acaba-en-2027-la-corte-constitucional-aclaro-que-pasara-con-el-auxilio-funerario-de-colpensiones/202655/
A76: ART_030 | B76: ART_030_S02 | C76: Semana | D76: Política | E76: Noticia dura | F76: Thu, 03 Sep 2026 02:25:55 +0000 | G76: Según Valora Analitik, la decisión se conoció luego de que el alto tribunal revisara las disposiciones de la reforma que cambiarán las reglas del sistema de pensiones. | H76: La Corte Constitucional señaló que el auxilio funerario contemplado dentro del sistema pensional se mantendrá en Colombia a partir de 2027, despejando así una de las dudas que había surgido alrededor de la entrada en vigencia de la reforma pensional. | I76: Aunque el nuevo modelo traerá modificaciones para los afiliados, la prestación destinada a cubrir parte de los gastos funerarios continuará vigente. | AD76: =IF(AND(COUNTIF($B$5:B76,B76)=1,$B76<>"",$AB76<>""),1,0) | AE76: https://www.semana.com/economia/management/articulo/se-acaba-en-2027-la-corte-constitucional-aclaro-que-pasara-con-el-auxilio-funerario-de-colpensiones/202655/
A77: ART_030 | B77: ART_030_S03 | C77: Semana | D77: Política | E77: Noticia dura | F77: Thu, 03 Sep 2026 02:25:55 +0000 | G77: Aunque el nuevo modelo traerá modificaciones para los afiliados, la prestación destinada a cubrir parte de los gastos funerarios continuará vigente. | H77: Según Valora Analitik, la decisión se conoció luego de que el alto tribunal revisara las disposiciones de la reforma que cambiarán las reglas del sistema de pensiones. | I77: El auxilio funerario es un reconocimiento económico que puede recibir la persona que demuestre haber asumido los gastos del funeral de un afiliado o pensionado fallecido. | AD77: =IF(AND(COUNTIF($B$5:B77,B77)=1,$B77<>"",$AB77<>""),1,0) | AE77: https://www.semana.com/economia/management/articulo/se-acaba-en-2027-la-corte-constitucional-aclaro-que-pasara-con-el-auxilio-funerario-de-colpensiones/202655/
A78: ART_030 | B78: ART_030_S04 | C78: Semana | D78: Política | E78: Noticia dura | F78: Thu, 03 Sep 2026 02:25:55 +0000 | G78: El auxilio funerario es un reconocimiento económico que puede recibir la persona que demuestre haber asumido los gastos del funeral de un afiliado o pensionado fallecido. | H78: Aunque el nuevo modelo traerá modificaciones para los afiliados, la prestación destinada a cubrir parte de los gastos funerarios continuará vigente. | I78: Se trata de un apoyo que busca reducir el impacto económico que puede representar para una familia afrontar este tipo de gastos. | AD78: =IF(AND(COUNTIF($B$5:B78,B78)=1,$B78<>"",$AB78<>""),1,0) | AE78: https://www.semana.com/economia/management/articulo/se-acaba-en-2027-la-corte-constitucional-aclaro-que-pasara-con-el-auxilio-funerario-de-colpensiones/202655/
A79: ART_030 | B79: ART_030_S05 | C79: Semana | D79: Política | E79: Noticia dura | F79: Thu, 03 Sep 2026 02:25:55 +0000 | G79: Se trata de un apoyo que busca reducir el impacto económico que puede representar para una familia afrontar este tipo de gastos. | H79: El auxilio funerario es un reconocimiento económico que puede recibir la persona que demuestre haber asumido los gastos del funeral de un afiliado o pensionado fallecido. | I79: De acuerdo con lo establecido en las normas que regulan la prestación, el monto del auxilio está relacionado con la situación pensional o salarial que tenía la persona fallecida. | AD79: =IF(AND(COUNTIF($B$5:B79,B79)=1,$B79<>"",$AB79<>""),1,0) | AE79: https://www.semana.com/economia/management/articulo/se-acaba-en-2027-la-corte-constitucional-aclaro-que-pasara-con-el-auxilio-funerario-de-colpensiones/202655/
A80: ART_030 | B80: ART_030_S06 | C80: Semana | D80: Política | E80: Noticia dura | F80: Thu, 03 Sep 2026 02:25:55 +0000 | G80: De acuerdo con lo establecido en las normas que regulan la prestación, el monto del auxilio está relacionado con la situación pensional o salarial que tenía la persona fallecida. | H80: Se trata de un apoyo que busca reducir el impacto económico que puede representar para una familia afrontar este tipo de gastos. | I80: Además, existe un límite mínimo y máximo para determinar cuánto dinero puede recibir quien haga la reclamación. | AD80: =IF(AND(COUNTIF($B$5:B80,B80)=1,$B80<>"",$AB80<>""),1,0) | AE80: https://www.semana.com/economia/management/articulo/se-acaba-en-2027-la-corte-constitucional-aclaro-que-pasara-con-el-auxilio-funerario-de-colpensiones/202655/
A81: ART_030 | B81: ART_030_S07 | C81: Semana | D81: Política | E81: Noticia dura | F81: Thu, 03 Sep 2026 02:25:55 +0000 | G81: Además, existe un límite mínimo y máximo para determinar cuánto dinero puede recibir quien haga la reclamación. | H81: De acuerdo con lo establecido en las normas que regulan la prestación, el monto del auxilio está relacionado con la situación pensional o salarial que tenía la persona fallecida. | I81: Con la decisión de la Corte, este beneficio no quedará eliminado cuando empiece a aplicarse el nuevo sistema pensional. | AD81: =IF(AND(COUNTIF($B$5:B81,B81)=1,$B81<>"",$AB81<>""),1,0) | AE81: https://www.semana.com/economia/management/articulo/se-acaba-en-2027-la-corte-constitucional-aclaro-que-pasara-con-el-auxilio-funerario-de-colpensiones/202655/
A82: ART_030 | B82: ART_030_S08 | C82: Semana | D82: Política | E82: Noticia dura | F82: Thu, 03 Sep 2026 02:25:55 +0000 | G82: Con la decisión de la Corte, este beneficio no quedará eliminado cuando empiece a aplicarse el nuevo sistema pensional. | H82: Además, existe un límite mínimo y máximo para determinar cuánto dinero puede recibir quien haga la reclamación. | I82: Sin embargo, el valor exacto que tendrá el auxilio en 2027 todavía no se puede establecer, pues uno de los factores utilizados para calcularlo depende del salario mínimo que sea fijado para ese año. | AD82: =IF(AND(COUNTIF($B$5:B82,B82)=1,$B82<>"",$AB82<>""),1,0) | AE82: https://www.semana.com/economia/management/articulo/se-acaba-en-2027-la-corte-constitucional-aclaro-que-pasara-con-el-auxilio-funerario-de-colpensiones/202655/
A83: ART_030 | B83: ART_030_S09 | C83: Semana | D83: Política | E83: Noticia dura | F83: Thu, 03 Sep 2026 02:25:55 +0000 | G83: Sin embargo, el valor exacto que tendrá el auxilio en 2027 todavía no se puede establecer, pues uno de los factores utilizados para calcularlo depende del salario mínimo que sea fijado para ese año. | H83: Con la decisión de la Corte, este beneficio no quedará eliminado cuando empiece a aplicarse el nuevo sistema pensional. | I83: Actualmente, la legislación contempla que el auxilio funerario debe estar dentro de un rango que va de cinco a diez salarios mínimos mensuales. | AD83: =IF(AND(COUNTIF($B$5:B83,B83)=1,$B83<>"",$AB83<>""),1,0) | AE83: https://www.semana.com/economia/management/articulo/se-acaba-en-2027-la-corte-constitucional-aclaro-que-pasara-con-el-auxilio-funerario-de-colpensiones/202655/
A84: ART_030 | B84: ART_030_S10 | C84: Semana | D84: Política | E84: Noticia dura | F84: Thu, 03 Sep 2026 02:25:55 +0000 | G84: Actualmente, la legislación contempla que el auxilio funerario debe estar dentro de un rango que va de cinco a diez salarios mínimos mensuales. | H84: Sin embargo, el valor exacto que tendrá el auxilio en 2027 todavía no se puede establecer, pues uno de los factores utilizados para calcularlo depende del salario mínimo que sea fijado para ese año. | AD84: =IF(AND(COUNTIF($B$5:B84,B84)=1,$B84<>"",$AB84<>""),1,0) | AE84: https://www.semana.com/economia/management/articulo/se-acaba-en-2027-la-corte-constitucional-aclaro-que-pasara-con-el-auxilio-funerario-de-colpensiones/202655/
A85: ART_031 | B85: ART_031_S01 | C85: Semana | D85: Política | E85: Noticia dura | F85: 2026-08-03T22:17:10-05:00 | G85: Veinticinco estados demócratas demandaron el lunes al gobierno federal estadounidense al considerar que la nueva política arancelaria del presidente Donald Trump excede sus poderes. | I85: El gobierno Trump anunció el 23 de julio aranceles generalizados de entre el 10 % y el 12,5 % sobre 60 socios comerciales de Estados Unidos, luego de una investigación que los acusa de permitir el suministro de bienes de países que recurren a trabajo forzado. | AD85: =IF(AND(COUNTIF($B$5:B85,B85)=1,$B85<>"",$AB85<>""),1,0) | AE85: https://www.semana.com/mundo/articulo/nueva-demanda-contra-aranceles-de-donald-trump-medidas-contra-colombia-podrian-caerse/202610/
A86: ART_031 | B86: ART_031_S02 | C86: Semana | D86: Política | E86: Noticia dura | F86: 2026-08-03T22:17:10-05:00 | G86: El gobierno Trump anunció el 23 de julio aranceles generalizados de entre el 10 % y el 12,5 % sobre 60 socios comerciales de Estados Unidos, luego de una investigación que los acusa de permitir el suministro de bienes de países que recurren a trabajo forzado. | H86: Veinticinco estados demócratas demandaron el lunes al gobierno federal estadounidense al considerar que la nueva política arancelaria del presidente Donald Trump excede sus poderes. | I86: Entre dichos países, estaba incluido Colombia, donde se aplicó gravamen del 12,5%. | AD86: =IF(AND(COUNTIF($B$5:B86,B86)=1,$B86<>"",$AB86<>""),1,0) | AE86: https://www.semana.com/mundo/articulo/nueva-demanda-contra-aranceles-de-donald-trump-medidas-contra-colombia-podrian-caerse/202610/
A87: ART_031 | B87: ART_031_S03 | C87: Semana | D87: Política | E87: Noticia dura | F87: 2026-08-03T22:17:10-05:00 | G87: Entre dichos países, estaba incluido Colombia, donde se aplicó gravamen del 12,5%. | H87: El gobierno Trump anunció el 23 de julio aranceles generalizados de entre el 10 % y el 12,5 % sobre 60 socios comerciales de Estados Unidos, luego de una investigación que los acusa de permitir el suministro de bienes de países que recurren a trabajo forzado. | I87: “No existe una relación racional entre el supuesto problema del trabajo forzado en las cadenas de suministro internacionales y los aranceles globales generalizados” que impuso la oficina del Representante Comercial (USTR), argumentó la coalición de estados en su demanda. | AD87: =IF(AND(COUNTIF($B$5:B87,B87)=1,$B87<>"",$AB87<>""),1,0) | AE87: https://www.semana.com/mundo/articulo/nueva-demanda-contra-aranceles-de-donald-trump-medidas-contra-colombia-podrian-caerse/202610/
A88: ART_031 | B88: ART_031_S04 | C88: Semana | D88: Política | E88: Noticia dura | F88: 2026-08-03T22:17:10-05:00 | G88: “No existe una relación racional entre el supuesto problema del trabajo forzado en las cadenas de suministro internacionales y los aranceles globales generalizados” que impuso la oficina del Representante Comercial (USTR), argumentó la coalición de estados en su demanda. | H88: Entre dichos países, estaba incluido Colombia, donde se aplicó gravamen del 12,5%. | I88: Los aranceles se impusieron tras investigaciones de la USTR sobre denuncias de “trabajo forzado”, realizadas en virtud de la Sección 301 de la Ley de Comercio de 1974. | AD88: =IF(AND(COUNTIF($B$5:B88,B88)=1,$B88<>"",$AB88<>""),1,0) | AE88: https://www.semana.com/mundo/articulo/nueva-demanda-contra-aranceles-de-donald-trump-medidas-contra-colombia-podrian-caerse/202610/
A89: ART_031 | B89: ART_031_S05 | C89: Semana | D89: Política | E89: Noticia dura | F89: 2026-08-03T22:17:10-05:00 | G89: Los aranceles se impusieron tras investigaciones de la USTR sobre denuncias de “trabajo forzado”, realizadas en virtud de la Sección 301 de la Ley de Comercio de 1974. | H89: “No existe una relación racional entre el supuesto problema del trabajo forzado en las cadenas de suministro internacionales y los aranceles globales generalizados” que impuso la oficina del Representante Comercial (USTR), argumentó la coalición de estados en su demanda. | I89: En una declaración transmitida a la AFP, el portavoz de la Casa Blanca, Kush Desai, aseguró que “Estados Unidos está utilizando su autoridad legal para lograr la eliminación de políticas, actos irrazonables y prácticas que perjudican el comercio estadounidense”. | AD89: =IF(AND(COUNTIF($B$5:B89,B89)=1,$B89<>"",$AB89<>""),1,0) | AE89: https://www.semana.com/mundo/articulo/nueva-demanda-contra-aranceles-de-donald-trump-medidas-contra-colombia-podrian-caerse/202610/
A90: ART_031 | B90: ART_031_S06 | C90: Semana | D90: Política | E90: Noticia dura | F90: 2026-08-03T22:17:10-05:00 | G90: En una declaración transmitida a la AFP, el portavoz de la Casa Blanca, Kush Desai, aseguró que “Estados Unidos está utilizando su autoridad legal para lograr la eliminación de políticas, actos irrazonables y prácticas que perjudican el comercio estadounidense”. | H90: Los aranceles se impusieron tras investigaciones de la USTR sobre denuncias de “trabajo forzado”, realizadas en virtud de la Sección 301 de la Ley de Comercio de 1974. | I90: Washington considera que la mayoría de sus socios comerciales, como la Unión Europea, no se atiene a las mismas exigencias de lucha contra el trabajo forzado que mantiene Estados Unidos. | AD90: =IF(AND(COUNTIF($B$5:B90,B90)=1,$B90<>"",$AB90<>""),1,0) | AE90: https://www.semana.com/mundo/articulo/nueva-demanda-contra-aranceles-de-donald-trump-medidas-contra-colombia-podrian-caerse/202610/
A91: ART_031 | B91: ART_031_S07 | C91: Semana | D91: Política | E91: Noticia dura | F91: 2026-08-03T22:17:10-05:00 | G91: Washington considera que la mayoría de sus socios comerciales, como la Unión Europea, no se atiene a las mismas exigencias de lucha contra el trabajo forzado que mantiene Estados Unidos. | H91: En una declaración transmitida a la AFP, el portavoz de la Casa Blanca, Kush Desai, aseguró que “Estados Unidos está utilizando su autoridad legal para lograr la eliminación de políticas, actos irrazonables y prácticas que perjudican el comercio estadounidense”. | I91: Desde que asumió el cargo por su segundo mandato, Trump ha trastocado el comercio mundial al imponer aranceles de amplio alcance tanto a aliados como a adversarios. | AD91: =IF(AND(COUNTIF($B$5:B91,B91)=1,$B91<>"",$AB91<>""),1,0) | AE91: https://www.semana.com/mundo/articulo/nueva-demanda-contra-aranceles-de-donald-trump-medidas-contra-colombia-podrian-caerse/202610/
A92: ART_031 | B92: ART_031_S08 | C92: Semana | D92: Política | E92: Noticia dura | F92: 2026-08-03T22:17:10-05:00 | G92: Desde que asumió el cargo por su segundo mandato, Trump ha trastocado el comercio mundial al imponer aranceles de amplio alcance tanto a aliados como a adversarios. | H92: Washington considera que la mayoría de sus socios comerciales, como la Unión Europea, no se atiene a las mismas exigencias de lucha contra el trabajo forzado que mantiene Estados Unidos. | I92: El mandatario ha sostenido que los socios comerciales de Estados Unidos se han estado aprovechando de la mayor economía del mundo y ha buscado utilizar los aranceles como palanca para lograr nuevos acuerdos comerciales. | AD92: =IF(AND(COUNTIF($B$5:B92,B92)=1,$B92<>"",$AB92<>""),1,0) | AE92: https://www.semana.com/mundo/articulo/nueva-demanda-contra-aranceles-de-donald-trump-medidas-contra-colombia-podrian-caerse/202610/
A93: ART_031 | B93: ART_031_S09 | C93: Semana | D93: Política | E93: Noticia dura | F93: 2026-08-03T22:17:10-05:00 | G93: El mandatario ha sostenido que los socios comerciales de Estados Unidos se han estado aprovechando de la mayor economía del mundo y ha buscado utilizar los aranceles como palanca para lograr nuevos acuerdos comerciales. | H93: Desde que asumió el cargo por su segundo mandato, Trump ha trastocado el comercio mundial al imponer aranceles de amplio alcance tanto a aliados como a adversarios. | I93: Su primera ronda de aranceles fue anulada por la Corte Suprema de Estados Unidos en febrero, por lo que Trump los reemplazó con un gravamen global del 10 %. | AD93: =IF(AND(COUNTIF($B$5:B93,B93)=1,$B93<>"",$AB93<>""),1,0) | AE93: https://www.semana.com/mundo/articulo/nueva-demanda-contra-aranceles-de-donald-trump-medidas-contra-colombia-podrian-caerse/202610/
A94: ART_031 | B94: ART_031_S10 | C94: Semana | D94: Política | E94: Noticia dura | F94: 2026-08-03T22:17:10-05:00 | G94: Su primera ronda de aranceles fue anulada por la Corte Suprema de Estados Unidos en febrero, por lo que Trump los reemplazó con un gravamen global del 10 %. | H94: El mandatario ha sostenido que los socios comerciales de Estados Unidos se han estado aprovechando de la mayor economía del mundo y ha buscado utilizar los aranceles como palanca para lograr nuevos acuerdos comerciales. | AD94: =IF(AND(COUNTIF($B$5:B94,B94)=1,$B94<>"",$AB94<>""),1,0) | AE94: https://www.semana.com/mundo/articulo/nueva-demanda-contra-aranceles-de-donald-trump-medidas-contra-colombia-podrian-caerse/202610/
A95: ART_032 | B95: ART_032_S01 | C95: Semana | D95: Política | E95: Opinión-análisis | F95: Fri, 04 Sep 2026 10:00:00 +0000 | G95: Mucho se ha hablado del “histórico megaacuerdo” petrolero entre los Estados Unidos y Venezuela. | I95: Dejando de lado las consideraciones legales y políticas que pudiera tener, habrá que saber cuáles son las eventuales consecuencias que podría tener para nuestro país. | AD95: =IF(AND(COUNTIF($B$5:B95,B95)=1,$B95<>"",$AB95<>""),1,0) | AE95: https://www.semana.com/opinion/articulo/una-venezuela-prospera-y-democratica-fundamental-para-colombia/202600/
A96: ART_032 | B96: ART_032_S02 | C96: Semana | D96: Política | E96: Opinión-análisis | F96: Fri, 04 Sep 2026 10:00:00 +0000 | G96: Dejando de lado las consideraciones legales y políticas que pudiera tener, habrá que saber cuáles son las eventuales consecuencias que podría tener para nuestro país. | H96: Mucho se ha hablado del “histórico megaacuerdo” petrolero entre los Estados Unidos y Venezuela. | I96: Hay hechos que son determinantes y que se derivan del transcurrir de los años de existencia de las dos repúblicas. | AD96: =IF(AND(COUNTIF($B$5:B96,B96)=1,$B96<>"",$AB96<>""),1,0) | AE96: https://www.semana.com/opinion/articulo/una-venezuela-prospera-y-democratica-fundamental-para-colombia/202600/
A97: ART_032 | B97: ART_032_S03 | C97: Semana | D97: Política | E97: Opinión-análisis | F97: Fri, 04 Sep 2026 10:00:00 +0000 | G97: Hay hechos que son determinantes y que se derivan del transcurrir de los años de existencia de las dos repúblicas. | H97: Dejando de lado las consideraciones legales y políticas que pudiera tener, habrá que saber cuáles son las eventuales consecuencias que podría tener para nuestro país. | I97: Ante todo, Colombia no tiene los recursos que posee Venezuela. | AD97: =IF(AND(COUNTIF($B$5:B97,B97)=1,$B97<>"",$AB97<>""),1,0) | AE97: https://www.semana.com/opinion/articulo/una-venezuela-prospera-y-democratica-fundamental-para-colombia/202600/
A98: ART_032 | B98: ART_032_S04 | C98: Semana | D98: Política | E98: Opinión-análisis | F98: Fri, 04 Sep 2026 10:00:00 +0000 | G98: Ante todo, Colombia no tiene los recursos que posee Venezuela. | H98: Hay hechos que son determinantes y que se derivan del transcurrir de los años de existencia de las dos repúblicas. | I98: Se recuerda a algún personaje colombiano que decía a mediados del siglo XX que, por cualquier parte por donde se trazara la línea fronteriza con Venezuela, el petróleo siempre estaría del otro lado. | AD98: =IF(AND(COUNTIF($B$5:B98,B98)=1,$B98<>"",$AB98<>""),1,0) | AE98: https://www.semana.com/opinion/articulo/una-venezuela-prospera-y-democratica-fundamental-para-colombia/202600/
A99: ART_032 | B99: ART_032_S05 | C99: Semana | D99: Política | E99: Opinión-análisis | F99: Fri, 04 Sep 2026 10:00:00 +0000 | G99: Se recuerda a algún personaje colombiano que decía a mediados del siglo XX que, por cualquier parte por donde se trazara la línea fronteriza con Venezuela, el petróleo siempre estaría del otro lado. | H99: Ante todo, Colombia no tiene los recursos que posee Venezuela. | I99: No solamente es el petróleo, sino el gas, el hierro, la bauxita, el acero, el coltán, las tierras raras y la energía eléctrica, para no hablar del oro y de algunos otros metales preciosos. | AD99: =IF(AND(COUNTIF($B$5:B99,B99)=1,$B99<>"",$AB99<>""),1,0) | AE99: https://www.semana.com/opinion/articulo/una-venezuela-prospera-y-democratica-fundamental-para-colombia/202600/
A100: ART_032 | B100: ART_032_S06 | C100: Semana | D100: Política | E100: Opinión-análisis | F100: Fri, 04 Sep 2026 10:00:00 +0000 | G100: No solamente es el petróleo, sino el gas, el hierro, la bauxita, el acero, el coltán, las tierras raras y la energía eléctrica, para no hablar del oro y de algunos otros metales preciosos. | H100: Se recuerda a algún personaje colombiano que decía a mediados del siglo XX que, por cualquier parte por donde se trazara la línea fronteriza con Venezuela, el petróleo siempre estaría del otro lado. | I100: En esas condiciones, a Colombia le interesa tener como vecina no solo a una Venezuela rica y floreciente, sino también democrática, aunque eso resulte más difícil, ya que gran parte de la vida republicana de la hermana república ha estado enmarcada dentro de gobiernos militares o sostenidos por ellos, incluso en gobiernos democráticos, en los que el estamento militar ha sido determinante. | AD100: =IF(AND(COUNTIF($B$5:B100,B100)=1,$B100<>"",$AB100<>""),1,0) | AE100: https://www.semana.com/opinion/articulo/una-venezuela-prospera-y-democratica-fundamental-para-colombia/202600/
A101: ART_032 | B101: ART_032_S07 | C101: Semana | D101: Política | E101: Opinión-análisis | F101: Fri, 04 Sep 2026 10:00:00 +0000 | G101: En esas condiciones, a Colombia le interesa tener como vecina no solo a una Venezuela rica y floreciente, sino también democrática, aunque eso resulte más difícil, ya que gran parte de la vida republicana de la hermana república ha estado enmarcada dentro de gobiernos militares o sostenidos por ellos, incluso en gobiernos democráticos, en los que el estamento militar ha sido determinante. | H101: No solamente es el petróleo, sino el gas, el hierro, la bauxita, el acero, el coltán, las tierras raras y la energía eléctrica, para no hablar del oro y de algunos otros metales preciosos. | I101: A esa condición se ha acostumbrado la población, a la que además le gustan los militares, que son los que dicen la última palabra, incluso en asuntos que van desde la política exterior hasta el manejo de la economía. | AD101: =IF(AND(COUNTIF($B$5:B101,B101)=1,$B101<>"",$AB101<>""),1,0) | AE101: https://www.semana.com/opinion/articulo/una-venezuela-prospera-y-democratica-fundamental-para-colombia/202600/
...
